{
"meta":{"test_sets":[],"test_metrics":[],"learn_metrics":[{"best_value":"Min","name":"Logloss"}],"launch_mode":"Train","parameters":"","iteration_count":1000,"learn_sets":["learn"],"name":"experiment"},
"iterations":[
{"learn":[0.5932481727],"iteration":0,"passed_time":0.230506788,"remaining_time":230.2762812},
{"learn":[0.5238656416],"iteration":1,"passed_time":0.2984875521,"remaining_time":148.9452885},
{"learn":[0.4511657825],"iteration":2,"passed_time":0.3678519392,"remaining_time":122.2494611},
{"learn":[0.4125506773],"iteration":3,"passed_time":0.4446179899,"remaining_time":110.7098795},
{"learn":[0.3703012401],"iteration":4,"passed_time":0.5165445983,"remaining_time":102.7923751},
{"learn":[0.3351571902],"iteration":5,"passed_time":0.5802136244,"remaining_time":96.12205711},
{"learn":[0.3091758247],"iteration":6,"passed_time":0.6477791949,"remaining_time":91.89210579},
{"learn":[0.2894829584],"iteration":7,"passed_time":0.7162088483,"remaining_time":88.80989719},
{"learn":[0.2735780737],"iteration":8,"passed_time":0.7858381798,"remaining_time":86.52951513},
{"learn":[0.2609140713],"iteration":9,"passed_time":0.8489828311,"remaining_time":84.04930028},
{"learn":[0.2461382449],"iteration":10,"passed_time":0.9258726415,"remaining_time":83.2443675},
{"learn":[0.2372126223],"iteration":11,"passed_time":0.9917696402,"remaining_time":81.65570037},
{"learn":[0.2320921576],"iteration":12,"passed_time":1.054284071,"remaining_time":80.04449061},
{"learn":[0.2244468301],"iteration":13,"passed_time":1.122537903,"remaining_time":79.0587409},
{"learn":[0.2136433682],"iteration":14,"passed_time":1.18915794,"remaining_time":78.08803806},
{"learn":[0.205648311],"iteration":15,"passed_time":1.257229612,"remaining_time":77.31962114},
{"learn":[0.202600383],"iteration":16,"passed_time":1.323608693,"remaining_time":76.53572617},
{"learn":[0.1964062351],"iteration":17,"passed_time":1.391722646,"remaining_time":75.92620215},
{"learn":[0.1940188119],"iteration":18,"passed_time":1.455850494,"remaining_time":75.16785973},
{"learn":[0.1915591178],"iteration":19,"passed_time":1.519967436,"remaining_time":74.47840435},
{"learn":[0.1898187374],"iteration":20,"passed_time":1.582387844,"remaining_time":73.76941427},
{"learn":[0.1860513015],"iteration":21,"passed_time":1.648358191,"remaining_time":73.27701413},
{"learn":[0.1850891335],"iteration":22,"passed_time":1.712501747,"remaining_time":72.74409594},
{"learn":[0.1820662121],"iteration":23,"passed_time":1.785031828,"remaining_time":72.59129432},
{"learn":[0.1795041005],"iteration":24,"passed_time":1.843994623,"remaining_time":71.9157903},
{"learn":[0.1775796421],"iteration":25,"passed_time":1.908619034,"remaining_time":71.49980534},
{"learn":[0.1760702822],"iteration":26,"passed_time":1.962157003,"remaining_time":70.71032458},
{"learn":[0.1738656593],"iteration":27,"passed_time":2.02450949,"remaining_time":70.27940088},
{"learn":[0.1716947873],"iteration":28,"passed_time":2.088324405,"remaining_time":69.92286197},
{"learn":[0.1712370905],"iteration":29,"passed_time":2.154008899,"remaining_time":69.64628774},
{"learn":[0.1700479187],"iteration":30,"passed_time":2.215894407,"remaining_time":69.26457032},
{"learn":[0.1679037659],"iteration":31,"passed_time":2.279125866,"remaining_time":68.94355744},
{"learn":[0.1662607323],"iteration":32,"passed_time":2.345980249,"remaining_time":68.74433033},
{"learn":[0.1644771946],"iteration":33,"passed_time":2.415778324,"remaining_time":68.63652533},
{"learn":[0.1637525849],"iteration":34,"passed_time":2.477348283,"remaining_time":68.30403124},
{"learn":[0.162958411],"iteration":35,"passed_time":2.550846031,"remaining_time":68.30598815},
{"learn":[0.1627016532],"iteration":36,"passed_time":2.611607518,"remaining_time":67.97237944},
{"learn":[0.1624587424],"iteration":37,"passed_time":2.674520771,"remaining_time":67.70760478},
{"learn":[0.1611759972],"iteration":38,"passed_time":2.737853577,"remaining_time":67.4635202},
{"learn":[0.1603359482],"iteration":39,"passed_time":2.801939614,"remaining_time":67.24655074},
{"learn":[0.1596795019],"iteration":40,"passed_time":2.862769797,"remaining_time":66.96088379},
{"learn":[0.1586157114],"iteration":41,"passed_time":2.922982324,"remaining_time":66.67183492},
{"learn":[0.1571543322],"iteration":42,"passed_time":2.995276548,"remaining_time":66.66231759},
{"learn":[0.1569994093],"iteration":43,"passed_time":3.060236006,"remaining_time":66.49058232},
{"learn":[0.1558567642],"iteration":44,"passed_time":3.12313442,"remaining_time":66.27985269},
{"learn":[0.1542049905],"iteration":45,"passed_time":3.192121295,"remaining_time":66.20181989},
{"learn":[0.1533795699],"iteration":46,"passed_time":3.253379493,"remaining_time":65.96746078},
{"learn":[0.1527263998],"iteration":47,"passed_time":3.319399433,"remaining_time":65.83475541},
{"learn":[0.1512379055],"iteration":48,"passed_time":3.43348281,"remaining_time":66.63759494},
{"learn":[0.1505408358],"iteration":49,"passed_time":3.53197368,"remaining_time":67.10749992},
{"learn":[0.1503981487],"iteration":50,"passed_time":3.639687136,"remaining_time":67.72672729},
{"learn":[0.1489622768],"iteration":51,"passed_time":3.756407521,"remaining_time":68.48219866},
{"learn":[0.1482767906],"iteration":52,"passed_time":3.861747216,"remaining_time":69.0014078},
{"learn":[0.1465499121],"iteration":53,"passed_time":3.969438132,"remaining_time":69.53867542},
{"learn":[0.144709242],"iteration":54,"passed_time":4.074674018,"remaining_time":70.01030812},
{"learn":[0.1440130053],"iteration":55,"passed_time":4.198153435,"remaining_time":70.7688722},
{"learn":[0.1426020716],"iteration":56,"passed_time":4.309438906,"remaining_time":71.29475243},
{"learn":[0.1421582856],"iteration":57,"passed_time":4.430572819,"remaining_time":71.95861371},
{"learn":[0.1414744273],"iteration":58,"passed_time":4.580163621,"remaining_time":73.04972826},
{"learn":[0.1413371604],"iteration":59,"passed_time":4.770805926,"remaining_time":74.74262617},
{"learn":[0.1403062277],"iteration":60,"passed_time":5.084986951,"remaining_time":78.27545487},
{"learn":[0.1392507127],"iteration":61,"passed_time":5.244477116,"remaining_time":79.34386347},
{"learn":[0.1391590023],"iteration":62,"passed_time":5.376626147,"remaining_time":79.96664603},
{"learn":[0.1388226087],"iteration":63,"passed_time":5.506356389,"remaining_time":80.53046218},
{"learn":[0.1376044451],"iteration":64,"passed_time":5.640070287,"remaining_time":81.13024182},
{"learn":[0.1363809962],"iteration":65,"passed_time":5.806899691,"remaining_time":82.17642896},
{"learn":[0.13554754],"iteration":66,"passed_time":5.957649209,"remaining_time":82.96248824},
{"learn":[0.1343099543],"iteration":67,"passed_time":6.109464431,"remaining_time":83.73560073},
{"learn":[0.1337737985],"iteration":68,"passed_time":6.254130837,"remaining_time":84.38544651},
{"learn":[0.1337253597],"iteration":69,"passed_time":6.392318739,"remaining_time":84.92652039},
{"learn":[0.1334930195],"iteration":70,"passed_time":6.619698242,"remaining_time":86.61548826},
{"learn":[0.1328934961],"iteration":71,"passed_time":6.958079203,"remaining_time":89.68190973},
{"learn":[0.1325707663],"iteration":72,"passed_time":7.132588376,"remaining_time":90.57410171},
{"learn":[0.1320503739],"iteration":73,"passed_time":7.283911744,"remaining_time":91.14732803},
{"learn":[0.1317151701],"iteration":74,"passed_time":7.445055218,"remaining_time":91.82234769},
{"learn":[0.1313471905],"iteration":75,"passed_time":7.854138907,"remaining_time":95.48979407},
{"learn":[0.1308845713],"iteration":76,"passed_time":8.174124719,"remaining_time":97.98333916},
{"learn":[0.130553457],"iteration":77,"passed_time":8.508672176,"remaining_time":100.5768685},
{"learn":[0.1304665748],"iteration":78,"passed_time":8.766478631,"remaining_time":102.2016053},
{"learn":[0.130420479],"iteration":79,"passed_time":8.945448695,"remaining_time":102.87266},
{"learn":[0.1301655199],"iteration":80,"passed_time":9.073206851,"remaining_time":102.9416925},
{"learn":[0.1295346736],"iteration":81,"passed_time":9.17887554,"remaining_time":102.758631},
{"learn":[0.1293377414],"iteration":82,"passed_time":9.27705262,"remaining_time":102.4946657},
{"learn":[0.1292774432],"iteration":83,"passed_time":9.36663785,"remaining_time":102.1409556},
{"learn":[0.1287532928],"iteration":84,"passed_time":9.475382611,"remaining_time":101.9997069},
{"learn":[0.1279695879],"iteration":85,"passed_time":9.567074146,"remaining_time":101.6779741},
{"learn":[0.1278744047],"iteration":86,"passed_time":9.666903063,"remaining_time":101.4469252},
{"learn":[0.1275687799],"iteration":87,"passed_time":9.790261392,"remaining_time":101.462709},
{"learn":[0.126965898],"iteration":88,"passed_time":9.912852049,"remaining_time":101.467508},
{"learn":[0.1263657828],"iteration":89,"passed_time":10.17540147,"remaining_time":102.8846148},
{"learn":[0.126283122],"iteration":90,"passed_time":10.4644618,"remaining_time":104.5296239},
{"learn":[0.126238616],"iteration":91,"passed_time":10.66108737,"remaining_time":105.2202971},
{"learn":[0.1260028538],"iteration":92,"passed_time":10.82081634,"remaining_time":105.5320476},
{"learn":[0.1255557948],"iteration":93,"passed_time":11.03446582,"remaining_time":106.3534685},
{"learn":[0.1252432358],"iteration":94,"passed_time":11.19874113,"remaining_time":106.6827444},
{"learn":[0.1247462763],"iteration":95,"passed_time":11.38382583,"remaining_time":107.1976932},
{"learn":[0.12437995],"iteration":96,"passed_time":11.6089069,"remaining_time":108.0705457},
{"learn":[0.12398868],"iteration":97,"passed_time":11.73307835,"remaining_time":107.992211},
{"learn":[0.1239477675],"iteration":98,"passed_time":11.82153784,"remaining_time":107.5879353},
{"learn":[0.1238231744],"iteration":99,"passed_time":11.89429149,"remaining_time":107.0486234},
{"learn":[0.1227884783],"iteration":100,"passed_time":11.97186067,"remaining_time":106.5614133},
{"learn":[0.1227459014],"iteration":101,"passed_time":12.04305282,"remaining_time":106.0260925},
{"learn":[0.122703495],"iteration":102,"passed_time":12.11095401,"remaining_time":105.4711238},
{"learn":[0.1223579332],"iteration":103,"passed_time":12.18195109,"remaining_time":104.952194},
{"learn":[0.1219980059],"iteration":104,"passed_time":12.29173264,"remaining_time":104.7723877},
{"learn":[0.121697996],"iteration":105,"passed_time":12.4022461,"remaining_time":104.6000756},
{"learn":[0.1210105312],"iteration":106,"passed_time":12.48592209,"remaining_time":104.2049385},
{"learn":[0.1209553854],"iteration":107,"passed_time":12.56179476,"remaining_time":103.7511197},
{"learn":[0.1205195241],"iteration":108,"passed_time":12.64258743,"remaining_time":103.3444532},
{"learn":[0.1204859809],"iteration":109,"passed_time":12.71441501,"remaining_time":102.871176},
{"learn":[0.1204119757],"iteration":110,"passed_time":12.7858006,"remaining_time":102.4015922},
{"learn":[0.1202245013],"iteration":111,"passed_time":12.86069944,"remaining_time":101.9669741},
{"learn":[0.1201920903],"iteration":112,"passed_time":12.93071701,"remaining_time":101.500407},
{"learn":[0.1198871335],"iteration":113,"passed_time":13.00885751,"remaining_time":101.1039277},
{"learn":[0.1190663648],"iteration":114,"passed_time":13.08971421,"remaining_time":100.7338876},
{"learn":[0.1190187596],"iteration":115,"passed_time":13.16344438,"remaining_time":100.3145244},
{"learn":[0.1188393867],"iteration":116,"passed_time":13.23437933,"remaining_time":99.87997389},
{"learn":[0.1183885893],"iteration":117,"passed_time":13.30628199,"remaining_time":99.4588196},
{"learn":[0.1183586318],"iteration":118,"passed_time":13.37937965,"remaining_time":99.05238214},
{"learn":[0.1179880553],"iteration":119,"passed_time":13.44890159,"remaining_time":98.62527831},
{"learn":[0.1171572392],"iteration":120,"passed_time":13.52141844,"remaining_time":98.22584142},
{"learn":[0.1168984572],"iteration":121,"passed_time":13.59986004,"remaining_time":97.87440257},
{"learn":[0.1165791278],"iteration":122,"passed_time":13.68557961,"remaining_time":97.57929524},
{"learn":[0.1165341279],"iteration":123,"passed_time":13.9126355,"remaining_time":98.28603787},
{"learn":[0.1164465764],"iteration":124,"passed_time":14.06367616,"remaining_time":98.44573312},
{"learn":[0.1164121147],"iteration":125,"passed_time":14.23229795,"remaining_time":98.7224477},
{"learn":[0.1163590461],"iteration":126,"passed_time":14.38767896,"remaining_time":98.90113175},
{"learn":[0.1162803426],"iteration":127,"passed_time":14.52689426,"remaining_time":98.96446716},
{"learn":[0.116251812],"iteration":128,"passed_time":14.65758978,"remaining_time":98.96713723},
{"learn":[0.1162121149],"iteration":129,"passed_time":14.75635906,"remaining_time":98.75409522},
{"learn":[0.116172554],"iteration":130,"passed_time":14.85733076,"remaining_time":98.55740789},
{"learn":[0.1160387471],"iteration":131,"passed_time":14.966728,"remaining_time":98.417575},
{"learn":[0.1160034229],"iteration":132,"passed_time":15.0699918,"remaining_time":98.23821723},
{"learn":[0.1159814564],"iteration":133,"passed_time":15.13849722,"remaining_time":97.83536264},
{"learn":[0.1157690765],"iteration":134,"passed_time":15.20841338,"remaining_time":97.44650056},
{"learn":[0.1157131102],"iteration":135,"passed_time":15.27994019,"remaining_time":97.07256119},
{"learn":[0.1153894559],"iteration":136,"passed_time":15.36313868,"remaining_time":96.77655973},
{"learn":[0.1152560663],"iteration":137,"passed_time":15.47824908,"remaining_time":96.68297611},
{"learn":[0.1151177918],"iteration":138,"passed_time":15.57956621,"remaining_time":96.50364394},
{"learn":[0.1150793312],"iteration":139,"passed_time":15.75468091,"remaining_time":96.77875418},
{"learn":[0.1150306723],"iteration":140,"passed_time":15.92590433,"remaining_time":97.02377176},
{"learn":[0.1150002766],"iteration":141,"passed_time":16.16321253,"remaining_time":97.66222782},
{"learn":[0.1149565484],"iteration":142,"passed_time":16.3813049,"remaining_time":98.17327484},
{"learn":[0.114928033],"iteration":143,"passed_time":16.5145555,"remaining_time":98.1698577},
{"learn":[0.1148992254],"iteration":144,"passed_time":16.66589494,"remaining_time":98.27131153},
{"learn":[0.1147743261],"iteration":145,"passed_time":16.89849865,"remaining_time":98.84464277},
{"learn":[0.114693556],"iteration":146,"passed_time":17.07343882,"remaining_time":99.07240351},
{"learn":[0.1146551863],"iteration":147,"passed_time":17.19551984,"remaining_time":98.99042501},
{"learn":[0.1146176811],"iteration":148,"passed_time":17.32471645,"remaining_time":98.9485483},
{"learn":[0.1145940977],"iteration":149,"passed_time":17.47649827,"remaining_time":99.03349022},
{"learn":[0.1144130458],"iteration":150,"passed_time":17.62447751,"remaining_time":99.09391658},
{"learn":[0.1136395244],"iteration":151,"passed_time":17.83022506,"remaining_time":99.4738872},
{"learn":[0.1133609152],"iteration":152,"passed_time":18.00736326,"remaining_time":99.68782143},
{"learn":[0.1129923045],"iteration":153,"passed_time":18.13778687,"remaining_time":99.64004997},
{"learn":[0.112627733],"iteration":154,"passed_time":18.26592282,"remaining_time":99.57874054},
{"learn":[0.1125928085],"iteration":155,"passed_time":18.39017655,"remaining_time":99.49557057},
{"learn":[0.1124828762],"iteration":156,"passed_time":18.49474522,"remaining_time":99.30617972},
{"learn":[0.1124428166],"iteration":157,"passed_time":18.58890642,"remaining_time":99.06240005},
{"learn":[0.112417725],"iteration":158,"passed_time":18.69724138,"remaining_time":98.89547172},
{"learn":[0.1123910593],"iteration":159,"passed_time":18.77162588,"remaining_time":98.55103589},
{"learn":[0.112347383],"iteration":160,"passed_time":18.98676252,"remaining_time":98.94343946},
{"learn":[0.1121985539],"iteration":161,"passed_time":19.13720749,"remaining_time":98.99370293},
{"learn":[0.1121726156],"iteration":162,"passed_time":19.24386563,"remaining_time":98.81665971},
{"learn":[0.112135849],"iteration":163,"passed_time":19.35779912,"remaining_time":98.67756138},
{"learn":[0.1118771531],"iteration":164,"passed_time":19.46048261,"remaining_time":98.48183622},
{"learn":[0.1117930196],"iteration":165,"passed_time":19.52314145,"remaining_time":98.08614441},
{"learn":[0.1117551665],"iteration":166,"passed_time":19.58747203,"remaining_time":97.70277966},
{"learn":[0.1117380313],"iteration":167,"passed_time":19.6523781,"remaining_time":97.32606295},
{"learn":[0.111587613],"iteration":168,"passed_time":19.72049028,"remaining_time":96.96880133},
{"learn":[0.1115446302],"iteration":169,"passed_time":19.78629885,"remaining_time":96.60369441},
{"learn":[0.1115185917],"iteration":170,"passed_time":19.84796263,"remaining_time":96.22199427},
{"learn":[0.1114880584],"iteration":171,"passed_time":19.90986229,"remaining_time":95.84515104},
{"learn":[0.1114546027],"iteration":172,"passed_time":19.97941391,"remaining_time":95.50852778},
{"learn":[0.1114256452],"iteration":173,"passed_time":20.0398376,"remaining_time":95.13164286},
{"learn":[0.1113941494],"iteration":174,"passed_time":20.10278629,"remaining_time":94.77027822},
{"learn":[0.1113638741],"iteration":175,"passed_time":20.17357404,"remaining_time":94.44900575},
{"learn":[0.1113263314],"iteration":176,"passed_time":20.25150218,"remaining_time":94.16376435},
{"learn":[0.1113054613],"iteration":177,"passed_time":20.32177596,"remaining_time":93.84550473},
{"learn":[0.1112560798],"iteration":178,"passed_time":20.39492693,"remaining_time":93.54321235},
{"learn":[0.1112230227],"iteration":179,"passed_time":20.45758397,"remaining_time":93.1956603},
{"learn":[0.111194545],"iteration":180,"passed_time":20.52706074,"remaining_time":92.88211462},
{"learn":[0.1111303423],"iteration":181,"passed_time":20.58950721,"remaining_time":92.53965329},
{"learn":[0.1110943347],"iteration":182,"passed_time":20.65346053,"remaining_time":92.20697952},
{"learn":[0.1110577042],"iteration":183,"passed_time":20.7295868,"remaining_time":91.93121101},
{"learn":[0.1109241991],"iteration":184,"passed_time":20.80427979,"remaining_time":91.65128666},
{"learn":[0.1108922716],"iteration":185,"passed_time":20.87930313,"remaining_time":91.37501479},
{"learn":[0.1108464342],"iteration":186,"passed_time":20.95569774,"remaining_time":91.10685703},
{"learn":[0.1108204694],"iteration":187,"passed_time":21.03338741,"remaining_time":90.84633285},
{"learn":[0.1107888773],"iteration":188,"passed_time":21.12787422,"remaining_time":90.65982007},
{"learn":[0.110755863],"iteration":189,"passed_time":21.20758318,"remaining_time":90.41127566},
{"learn":[0.1107312655],"iteration":190,"passed_time":21.27546125,"remaining_time":90.11438824},
{"learn":[0.1106913788],"iteration":191,"passed_time":21.33762634,"remaining_time":89.79584419},
{"learn":[0.1106726353],"iteration":192,"passed_time":21.39885123,"remaining_time":89.47602562},
{"learn":[0.1106202475],"iteration":193,"passed_time":21.46229612,"remaining_time":89.16809624},
{"learn":[0.1105333195],"iteration":194,"passed_time":21.54213576,"remaining_time":88.93035531},
{"learn":[0.1105057641],"iteration":195,"passed_time":21.61715268,"remaining_time":88.67444262},
{"learn":[0.1104684523],"iteration":196,"passed_time":21.6797155,"remaining_time":88.36960177},
{"learn":[0.1104309001],"iteration":197,"passed_time":21.76899294,"remaining_time":88.17541585},
{"learn":[0.110389897],"iteration":198,"passed_time":21.83563568,"remaining_time":87.8911768},
{"learn":[0.1103606257],"iteration":199,"passed_time":21.89834562,"remaining_time":87.59338246},
{"learn":[0.1103370595],"iteration":200,"passed_time":21.95846334,"remaining_time":87.28762292},
{"learn":[0.1103084962],"iteration":201,"passed_time":22.01836526,"remaining_time":86.98344295},
{"learn":[0.1102776712],"iteration":202,"passed_time":22.0853922,"remaining_time":86.70964326},
{"learn":[0.1102514882],"iteration":203,"passed_time":22.15347563,"remaining_time":86.44199315},
{"learn":[0.1102219216],"iteration":204,"passed_time":22.21811321,"remaining_time":86.16292685},
{"learn":[0.1101935461],"iteration":205,"passed_time":22.28334714,"remaining_time":85.88824091},
{"learn":[0.1101684308],"iteration":206,"passed_time":22.34794118,"remaining_time":85.61312731},
{"learn":[0.1100495839],"iteration":207,"passed_time":22.41958883,"remaining_time":85.36689591},
{"learn":[0.1100152054],"iteration":208,"passed_time":22.4799977,"remaining_time":85.07979989},
{"learn":[0.1099645696],"iteration":209,"passed_time":22.54467077,"remaining_time":84.81090434},
{"learn":[0.1099361616],"iteration":210,"passed_time":22.60453489,"remaining_time":84.52596221},
{"learn":[0.1098667247],"iteration":211,"passed_time":22.67485438,"remaining_time":84.28200592},
{"learn":[0.1098459194],"iteration":212,"passed_time":22.74670077,"remaining_time":84.04532162},
{"learn":[0.1098166919],"iteration":213,"passed_time":22.81258925,"remaining_time":83.78829508},
{"learn":[0.1097954411],"iteration":214,"passed_time":22.87338072,"remaining_time":83.51443659},
{"learn":[0.1097596958],"iteration":215,"passed_time":22.9366793,"remaining_time":83.2516508},
{"learn":[0.1097268559],"iteration":216,"passed_time":22.99837565,"remaining_time":82.98492228},
{"learn":[0.1096980719],"iteration":217,"passed_time":23.06100855,"remaining_time":82.72343434},
{"learn":[0.1096560846],"iteration":218,"passed_time":23.12308241,"remaining_time":82.46176876},
{"learn":[0.1096314025],"iteration":219,"passed_time":23.18863652,"remaining_time":82.21425675},
{"learn":[0.1096105064],"iteration":220,"passed_time":23.24823355,"remaining_time":81.94739338},
{"learn":[0.1095685265],"iteration":221,"passed_time":23.32206002,"remaining_time":81.73226438},
{"learn":[0.1095325713],"iteration":222,"passed_time":23.39105122,"remaining_time":81.50155516},
{"learn":[0.1095154611],"iteration":223,"passed_time":23.458059,"remaining_time":81.26541869},
{"learn":[0.1094880963],"iteration":224,"passed_time":23.52574433,"remaining_time":81.03311935},
{"learn":[0.1094572624],"iteration":225,"passed_time":23.58840803,"remaining_time":80.78507882},
{"learn":[0.1093875896],"iteration":226,"passed_time":23.65335948,"remaining_time":80.54646201},
{"learn":[0.1093622115],"iteration":227,"passed_time":23.72582909,"remaining_time":80.3348248},
{"learn":[0.109321905],"iteration":228,"passed_time":23.79802289,"remaining_time":80.12347446},
{"learn":[0.1093016317],"iteration":229,"passed_time":23.8752522,"remaining_time":79.93019215},
{"learn":[0.1092779353],"iteration":230,"passed_time":23.94871909,"remaining_time":79.72538951},
{"learn":[0.1092474249],"iteration":231,"passed_time":24.01133822,"remaining_time":79.48580929},
{"learn":[0.1092258328],"iteration":232,"passed_time":24.07923484,"remaining_time":79.26512068},
{"learn":[0.1091863521],"iteration":233,"passed_time":24.14711257,"remaining_time":79.04567617},
{"learn":[0.1091362063],"iteration":234,"passed_time":24.22168082,"remaining_time":78.84930138},
{"learn":[0.1091147528],"iteration":235,"passed_time":24.28447729,"remaining_time":78.61585019},
{"learn":[0.1090784955],"iteration":236,"passed_time":24.34954605,"remaining_time":78.39115458},
{"learn":[0.1090546314],"iteration":237,"passed_time":24.41029276,"remaining_time":78.15396254},
{"learn":[0.1090200433],"iteration":238,"passed_time":24.47941414,"remaining_time":77.94491281},
{"learn":[0.1089882931],"iteration":239,"passed_time":24.55571835,"remaining_time":77.75977479},
{"learn":[0.1089557121],"iteration":240,"passed_time":24.62274576,"remaining_time":77.54632379},
{"learn":[0.1089377136],"iteration":241,"passed_time":24.6891851,"remaining_time":77.33224094},
{"learn":[0.1089072837],"iteration":242,"passed_time":24.76616027,"remaining_time":77.15219477},
{"learn":[0.1088883682],"iteration":243,"passed_time":24.8412337,"remaining_time":76.96710115},
{"learn":[0.108866017],"iteration":244,"passed_time":24.9186592,"remaining_time":76.79015387},
{"learn":[0.1088363054],"iteration":245,"passed_time":24.98064447,"remaining_time":76.56669076},
{"learn":[0.1088115837],"iteration":246,"passed_time":25.04768652,"remaining_time":76.3599512},
{"learn":[0.1087772322],"iteration":247,"passed_time":25.12463303,"remaining_time":76.18437112},
{"learn":[0.1087506322],"iteration":248,"passed_time":25.20138836,"remaining_time":76.00900667},
{"learn":[0.1086764601],"iteration":249,"passed_time":25.27010366,"remaining_time":75.81031097},
{"learn":[0.1086376246],"iteration":250,"passed_time":25.34688061,"remaining_time":75.63670749},
{"learn":[0.1085909911],"iteration":251,"passed_time":25.41913732,"remaining_time":75.45045521},
{"learn":[0.1085603915],"iteration":252,"passed_time":25.48363137,"remaining_time":75.24218433},
{"learn":[0.1085331814],"iteration":253,"passed_time":25.54440478,"remaining_time":75.02411797},
{"learn":[0.1085136886],"iteration":254,"passed_time":25.61631365,"remaining_time":74.83981832},
{"learn":[0.1084676563],"iteration":255,"passed_time":25.68728921,"remaining_time":74.65368428},
{"learn":[0.1084470071],"iteration":256,"passed_time":25.75701222,"remaining_time":74.46482521},
{"learn":[0.1084207714],"iteration":257,"passed_time":25.82209091,"remaining_time":74.26353276},
{"learn":[0.1083940611],"iteration":258,"passed_time":25.88733441,"remaining_time":74.06376371},
{"learn":[0.1083713223],"iteration":259,"passed_time":25.95213712,"remaining_time":73.86377489},
{"learn":[0.1083499504],"iteration":260,"passed_time":26.03850364,"remaining_time":73.72587811},
{"learn":[0.1083119129],"iteration":261,"passed_time":26.10920571,"remaining_time":73.5442512},
{"learn":[0.1082840777],"iteration":262,"passed_time":26.17947357,"remaining_time":73.36225104},
{"learn":[0.108208871],"iteration":263,"passed_time":26.24925513,"remaining_time":73.17974157},
{"learn":[0.1081804831],"iteration":264,"passed_time":26.32150143,"remaining_time":73.00491907},
{"learn":[0.1081466269],"iteration":265,"passed_time":26.39912233,"remaining_time":72.84569845},
{"learn":[0.108128806],"iteration":266,"passed_time":26.46821224,"remaining_time":72.66366882},
{"learn":[0.1080709752],"iteration":267,"passed_time":26.54630548,"remaining_time":72.50707318},
{"learn":[0.1080399081],"iteration":268,"passed_time":26.61774191,"remaining_time":72.33297151},
{"learn":[0.1080097366],"iteration":269,"passed_time":26.69452219,"remaining_time":72.17407851},
{"learn":[0.1079768435],"iteration":270,"passed_time":26.76791898,"remaining_time":72.00668981},
{"learn":[0.107941466],"iteration":271,"passed_time":26.8359692,"remaining_time":71.82568228},
{"learn":[0.1077742591],"iteration":272,"passed_time":26.91836916,"remaining_time":71.68371566},
{"learn":[0.1077438434],"iteration":273,"passed_time":26.99081108,"remaining_time":71.51579871},
{"learn":[0.1077077174],"iteration":274,"passed_time":27.06569856,"remaining_time":71.35502347},
{"learn":[0.1076813134],"iteration":275,"passed_time":27.1499547,"remaining_time":71.21944639},
{"learn":[0.1076630683],"iteration":276,"passed_time":27.21617555,"remaining_time":71.03716579},
{"learn":[0.1076407899],"iteration":277,"passed_time":27.28896444,"remaining_time":70.87277815},
{"learn":[0.1075366355],"iteration":278,"passed_time":27.36481712,"remaining_time":70.71696467},
{"learn":[0.1075062059],"iteration":279,"passed_time":27.44339601,"remaining_time":70.5687326},
{"learn":[0.1074618924],"iteration":280,"passed_time":27.5175404,"remaining_time":70.40964964},
{"learn":[0.1074288325],"iteration":281,"passed_time":27.5850597,"remaining_time":70.23430094},
{"learn":[0.1074027697],"iteration":282,"passed_time":27.65693892,"remaining_time":70.07076044},
{"learn":[0.1073418494],"iteration":283,"passed_time":27.72857876,"remaining_time":69.90726195},
{"learn":[0.1073135322],"iteration":284,"passed_time":27.8008497,"remaining_time":69.74599136},
{"learn":[0.1072845154],"iteration":285,"passed_time":27.87290667,"remaining_time":69.58480896},
{"learn":[0.1072429911],"iteration":286,"passed_time":27.95724299,"remaining_time":69.45475348},
{"learn":[0.1072102758],"iteration":287,"passed_time":28.02620006,"remaining_time":69.2869946},
{"learn":[0.1071903576],"iteration":288,"passed_time":28.09322818,"remaining_time":69.11517382},
{"learn":[0.1071603808],"iteration":289,"passed_time":28.17550629,"remaining_time":68.98141194},
{"learn":[0.1071195613],"iteration":290,"passed_time":28.25440544,"remaining_time":68.83977133},
{"learn":[0.1070940988],"iteration":291,"passed_time":28.3271573,"remaining_time":68.68365538},
{"learn":[0.1070778752],"iteration":292,"passed_time":28.39021519,"remaining_time":68.5047172},
{"learn":[0.1070572325],"iteration":293,"passed_time":28.45244024,"remaining_time":68.32456737},
{"learn":[0.1070101763],"iteration":294,"passed_time":28.54098122,"remaining_time":68.20810766},
{"learn":[0.1069877278],"iteration":295,"passed_time":28.61913573,"remaining_time":68.06713364},
{"learn":[0.1069668886],"iteration":296,"passed_time":28.69770865,"remaining_time":67.927573},
{"learn":[0.1069417672],"iteration":297,"passed_time":28.76493832,"remaining_time":67.76170034},
{"learn":[0.106927908],"iteration":298,"passed_time":28.83472905,"remaining_time":67.60249184},
{"learn":[0.1068991638],"iteration":299,"passed_time":28.90603044,"remaining_time":67.44740436},
{"learn":[0.1068692644],"iteration":300,"passed_time":28.97647752,"remaining_time":67.29088966},
{"learn":[0.1068455291],"iteration":301,"passed_time":29.05670977,"remaining_time":67.15756099},
{"learn":[0.1068158019],"iteration":302,"passed_time":29.13239891,"remaining_time":67.01413215},
{"learn":[0.1067860437],"iteration":303,"passed_time":29.20325243,"remaining_time":66.86007794},
{"learn":[0.1067678928],"iteration":304,"passed_time":29.27203787,"remaining_time":66.70185678},
{"learn":[0.1067338403],"iteration":305,"passed_time":29.34494642,"remaining_time":66.5535713},
{"learn":[0.1067096022],"iteration":306,"passed_time":29.42315359,"remaining_time":66.41773758},
{"learn":[0.106688411],"iteration":307,"passed_time":29.49418234,"remaining_time":66.26614994},
{"learn":[0.10666918],"iteration":308,"passed_time":29.57791668,"remaining_time":66.14349653},
{"learn":[0.1066530641],"iteration":309,"passed_time":29.64629169,"remaining_time":65.98690731},
{"learn":[0.1066045126],"iteration":310,"passed_time":29.73499318,"remaining_time":65.87591737},
{"learn":[0.1065650158],"iteration":311,"passed_time":29.80499612,"remaining_time":65.7238376},
{"learn":[0.1065337141],"iteration":312,"passed_time":29.87929725,"remaining_time":65.58171632},
{"learn":[0.1065164047],"iteration":313,"passed_time":29.95264022,"remaining_time":65.43793373},
{"learn":[0.1064825542],"iteration":314,"passed_time":30.04290054,"remaining_time":65.3313869},
{"learn":[0.1064578515],"iteration":315,"passed_time":30.12070968,"remaining_time":65.19799184},
{"learn":[0.1064330408],"iteration":316,"passed_time":30.21033283,"remaining_time":65.09040164},
{"learn":[0.1062834338],"iteration":317,"passed_time":30.29811003,"remaining_time":64.97896553},
{"learn":[0.10625474],"iteration":318,"passed_time":30.36650098,"remaining_time":64.82629205},
{"learn":[0.1062271256],"iteration":319,"passed_time":30.43947702,"remaining_time":64.68388866},
{"learn":[0.106201813],"iteration":320,"passed_time":30.50315216,"remaining_time":64.52224398},
{"learn":[0.1060947578],"iteration":321,"passed_time":30.57013022,"remaining_time":64.3681624},
{"learn":[0.1060562655],"iteration":322,"passed_time":30.63934218,"remaining_time":64.21930234},
{"learn":[0.1060373351],"iteration":323,"passed_time":30.70462994,"remaining_time":64.06274641},
{"learn":[0.1059998892],"iteration":324,"passed_time":30.76978761,"remaining_time":63.90648195},
{"learn":[0.1059817077],"iteration":325,"passed_time":30.82679341,"remaining_time":63.73392257},
{"learn":[0.1059620562],"iteration":326,"passed_time":30.89445482,"remaining_time":63.58400028},
{"learn":[0.1059425561],"iteration":327,"passed_time":30.95518242,"remaining_time":63.42037375},
{"learn":[0.1059117173],"iteration":328,"passed_time":31.01864689,"remaining_time":63.26295459},
{"learn":[0.1058935199],"iteration":329,"passed_time":31.07948692,"remaining_time":63.10077647},
{"learn":[0.1058621364],"iteration":330,"passed_time":31.15489917,"remaining_time":62.96866328},
{"learn":[0.1058399419],"iteration":331,"passed_time":31.21809104,"remaining_time":62.81230366},
{"learn":[0.1058067182],"iteration":332,"passed_time":31.28518374,"remaining_time":62.66431698},
{"learn":[0.1057781074],"iteration":333,"passed_time":31.35533201,"remaining_time":62.52290754},
{"learn":[0.1057565549],"iteration":334,"passed_time":31.42300993,"remaining_time":62.3770197},
{"learn":[0.1057229672],"iteration":335,"passed_time":31.48920918,"remaining_time":62.22867529},
{"learn":[0.1057016188],"iteration":336,"passed_time":31.55402692,"remaining_time":62.07810044},
{"learn":[0.1056638333],"iteration":337,"passed_time":31.61760155,"remaining_time":61.9255983},
{"learn":[0.1056266607],"iteration":338,"passed_time":31.68777177,"remaining_time":61.78648123},
{"learn":[0.1056054044],"iteration":339,"passed_time":31.7500535,"remaining_time":61.6324568},
{"learn":[0.1055673188],"iteration":340,"passed_time":31.81624701,"remaining_time":61.48653015},
{"learn":[0.1055448182],"iteration":341,"passed_time":31.88240472,"remaining_time":61.34100089},
{"learn":[0.1055198279],"iteration":342,"passed_time":31.95193307,"remaining_time":61.20239075},
{"learn":[0.1054782381],"iteration":343,"passed_time":32.01695099,"remaining_time":61.05558096},
{"learn":[0.1054385563],"iteration":344,"passed_time":32.08353712,"remaining_time":60.91222265},
{"learn":[0.1053918669],"iteration":345,"passed_time":32.15387329,"remaining_time":60.77639634},
{"learn":[0.105358617],"iteration":346,"passed_time":32.22607328,"remaining_time":60.6444549},
{"learn":[0.1053354933],"iteration":347,"passed_time":32.29123823,"remaining_time":60.49967622},
{"learn":[0.1053046114],"iteration":348,"passed_time":32.35912902,"remaining_time":60.36043838},
{"learn":[0.1052799834],"iteration":349,"passed_time":32.42759512,"remaining_time":60.22267665},
{"learn":[0.1052455942],"iteration":350,"passed_time":32.52284602,"remaining_time":60.13483495},
{"learn":[0.1052191374],"iteration":351,"passed_time":32.58901196,"remaining_time":59.99340839},
{"learn":[0.1052007637],"iteration":352,"passed_time":32.65412758,"remaining_time":59.85048312},
{"learn":[0.105181749],"iteration":353,"passed_time":32.71920427,"remaining_time":59.70792644},
{"learn":[0.1051580322],"iteration":354,"passed_time":32.78949427,"remaining_time":59.57527831},
{"learn":[0.105139454],"iteration":355,"passed_time":32.85397703,"remaining_time":59.4324753},
{"learn":[0.1051142153],"iteration":356,"passed_time":32.92218851,"remaining_time":59.29682692},
{"learn":[0.1049717056],"iteration":357,"passed_time":32.98671687,"remaining_time":59.15495036},
{"learn":[0.1049385821],"iteration":358,"passed_time":33.0498286,"remaining_time":59.01097529},
{"learn":[0.1049151543],"iteration":359,"passed_time":33.11283541,"remaining_time":58.86726295},
{"learn":[0.1048840583],"iteration":360,"passed_time":33.17640258,"remaining_time":58.72498961},
{"learn":[0.1048669977],"iteration":361,"passed_time":33.24008665,"remaining_time":58.58335714},
{"learn":[0.1048372745],"iteration":362,"passed_time":33.31495666,"remaining_time":58.46178344},
{"learn":[0.1047969706],"iteration":363,"passed_time":33.38136972,"remaining_time":58.32568994},
{"learn":[0.1047640438],"iteration":364,"passed_time":33.45128278,"remaining_time":58.1960673},
{"learn":[0.1047339981],"iteration":365,"passed_time":33.51966818,"remaining_time":58.06412467},
{"learn":[0.1047125027],"iteration":366,"passed_time":33.58882957,"remaining_time":57.9338668},
{"learn":[0.1046794707],"iteration":367,"passed_time":33.6509504,"remaining_time":57.7918496},
{"learn":[0.1046535505],"iteration":368,"passed_time":33.73057204,"remaining_time":57.6801923},
{"learn":[0.1046167067],"iteration":369,"passed_time":33.81221966,"remaining_time":57.5721578},
{"learn":[0.1046038768],"iteration":370,"passed_time":33.88076351,"remaining_time":57.44204919},
{"learn":[0.1045825664],"iteration":371,"passed_time":33.95109581,"remaining_time":57.31529078},
{"learn":[0.1045635114],"iteration":372,"passed_time":34.02407132,"remaining_time":57.19327807},
{"learn":[0.1045472629],"iteration":373,"passed_time":34.09369529,"remaining_time":57.06591779},
{"learn":[0.1045135825],"iteration":374,"passed_time":34.16733653,"remaining_time":56.94556088},
{"learn":[0.1045024428],"iteration":375,"passed_time":34.23885966,"remaining_time":56.8219373},
{"learn":[0.1044836426],"iteration":376,"passed_time":34.30247401,"remaining_time":56.68552071},
{"learn":[0.1044559825],"iteration":377,"passed_time":34.36988227,"remaining_time":56.5557322},
{"learn":[0.1044101654],"iteration":378,"passed_time":34.44382491,"remaining_time":56.4369796},
{"learn":[0.1043820924],"iteration":379,"passed_time":34.50410429,"remaining_time":56.29617016},
{"learn":[0.1043594508],"iteration":380,"passed_time":34.56765792,"remaining_time":56.16110303},
{"learn":[0.1043310535],"iteration":381,"passed_time":34.63637474,"remaining_time":56.03476333},
{"learn":[0.1042979793],"iteration":382,"passed_time":34.70044576,"remaining_time":55.9012403},
{"learn":[0.104273128],"iteration":383,"passed_time":34.76398518,"remaining_time":55.76722622},
{"learn":[0.1042354982],"iteration":384,"passed_time":34.82840009,"remaining_time":55.63497676},
{"learn":[0.1042027451],"iteration":385,"passed_time":34.89675815,"remaining_time":55.50935105},
{"learn":[0.104180873],"iteration":386,"passed_time":34.95741972,"remaining_time":55.3718302},
{"learn":[0.1041561727],"iteration":387,"passed_time":35.02603328,"remaining_time":55.24724837},
{"learn":[0.1041335267],"iteration":388,"passed_time":35.08950269,"remaining_time":55.11487441},
{"learn":[0.1041182175],"iteration":389,"passed_time":35.15582312,"remaining_time":54.98731309},
{"learn":[0.1041003624],"iteration":390,"passed_time":35.22019858,"remaining_time":54.85703564},
{"learn":[0.1039808834],"iteration":391,"passed_time":35.29035769,"remaining_time":54.73606498},
{"learn":[0.1039616874],"iteration":392,"passed_time":35.35244262,"remaining_time":54.60288211},
{"learn":[0.1039308467],"iteration":393,"passed_time":35.42239442,"remaining_time":54.48215994},
{"learn":[0.1038969329],"iteration":394,"passed_time":35.49080811,"remaining_time":54.35933901},
{"learn":[0.1038760487],"iteration":395,"passed_time":35.5553253,"remaining_time":54.23084971},
{"learn":[0.1038375862],"iteration":396,"passed_time":35.62091215,"remaining_time":54.10430737},
{"learn":[0.103815846],"iteration":397,"passed_time":35.68597197,"remaining_time":53.97727418},
{"learn":[0.1037913332],"iteration":398,"passed_time":35.74847963,"remaining_time":53.84670741},
{"learn":[0.10365333],"iteration":399,"passed_time":35.81790149,"remaining_time":53.72685223},
{"learn":[0.1036209455],"iteration":400,"passed_time":35.8864309,"remaining_time":53.60591549},
{"learn":[0.1035305461],"iteration":401,"passed_time":35.96105438,"remaining_time":53.49430478},
{"learn":[0.1035060972],"iteration":402,"passed_time":36.02050277,"remaining_time":53.3603974},
{"learn":[0.1034822312],"iteration":403,"passed_time":36.08559505,"remaining_time":53.23518478},
{"learn":[0.10347215],"iteration":404,"passed_time":36.14788562,"remaining_time":53.10615294},
{"learn":[0.1034437416],"iteration":405,"passed_time":36.21752933,"remaining_time":52.98820794},
{"learn":[0.1034191302],"iteration":406,"passed_time":36.28707451,"remaining_time":52.87035672},
{"learn":[0.1033924189],"iteration":407,"passed_time":36.3582921,"remaining_time":52.75516893},
{"learn":[0.1033025555],"iteration":408,"passed_time":36.42889868,"remaining_time":52.63931325},
{"learn":[0.1032721245],"iteration":409,"passed_time":36.49820348,"remaining_time":52.52180501},
{"learn":[0.1032419241],"iteration":410,"passed_time":36.56293901,"remaining_time":52.39798315},
{"learn":[0.1032014734],"iteration":411,"passed_time":36.63310665,"remaining_time":52.28220075},
{"learn":[0.1031814539],"iteration":412,"passed_time":36.70326978,"remaining_time":52.16663283},
{"learn":[0.1031550058],"iteration":413,"passed_time":36.76827514,"remaining_time":52.04398365},
{"learn":[0.1031361108],"iteration":414,"passed_time":36.8311945,"remaining_time":51.91867177},
{"learn":[0.1031006622],"iteration":415,"passed_time":36.89391948,"remaining_time":51.79338697},
{"learn":[0.103072938],"iteration":416,"passed_time":36.95857239,"remaining_time":51.67109761},
{"learn":[0.103040603],"iteration":417,"passed_time":37.02223544,"remaining_time":51.54770581},
{"learn":[0.1030093635],"iteration":418,"passed_time":37.09369483,"remaining_time":51.43540977},
{"learn":[0.1029880258],"iteration":419,"passed_time":37.15350026,"remaining_time":51.30721464},
{"learn":[0.1029563542],"iteration":420,"passed_time":37.22024669,"remaining_time":51.18889035},
{"learn":[0.1029374775],"iteration":421,"passed_time":37.28003857,"remaining_time":51.06128505},
{"learn":[0.1028972868],"iteration":422,"passed_time":37.35094419,"remaining_time":50.94916028},
{"learn":[0.1028716986],"iteration":423,"passed_time":37.42324558,"remaining_time":50.83912607},
{"learn":[0.1028580169],"iteration":424,"passed_time":37.49663327,"remaining_time":50.73073914},
{"learn":[0.1028330783],"iteration":425,"passed_time":37.56616445,"remaining_time":50.61732017},
{"learn":[0.1028166726],"iteration":426,"passed_time":37.62850031,"remaining_time":50.49445123},
{"learn":[0.1027909683],"iteration":427,"passed_time":37.69262073,"remaining_time":50.37425014},
{"learn":[0.1027704814],"iteration":428,"passed_time":37.76338333,"remaining_time":50.26315124},
{"learn":[0.1027436817],"iteration":429,"passed_time":37.83101879,"remaining_time":50.14809468},
{"learn":[0.1027114562],"iteration":430,"passed_time":37.90151834,"remaining_time":50.0370393},
{"learn":[0.1026829011],"iteration":431,"passed_time":37.96775674,"remaining_time":49.92056904},
{"learn":[0.1026670097],"iteration":432,"passed_time":38.03451551,"remaining_time":49.80501222},
{"learn":[0.1026416885],"iteration":433,"passed_time":38.09771328,"remaining_time":49.68503621},
{"learn":[0.1026217746],"iteration":434,"passed_time":38.15715656,"remaining_time":49.56044472},
{"learn":[0.1026047121],"iteration":435,"passed_time":38.21631096,"remaining_time":49.43577839},
{"learn":[0.1025780362],"iteration":436,"passed_time":38.28016642,"remaining_time":49.31746841},
{"learn":[0.1025566629],"iteration":437,"passed_time":38.34797224,"remaining_time":49.2044758},
{"learn":[0.102542525],"iteration":438,"passed_time":38.41274403,"remaining_time":49.08781184},
{"learn":[0.1025087005],"iteration":439,"passed_time":38.47907547,"remaining_time":48.97336878},
{"learn":[0.1024868696],"iteration":440,"passed_time":38.54520684,"remaining_time":48.8588903},
{"learn":[0.1024620943],"iteration":441,"passed_time":38.61789144,"remaining_time":48.75290368},
{"learn":[0.1024529304],"iteration":442,"passed_time":38.67758371,"remaining_time":48.63073167},
{"learn":[0.1023220699],"iteration":443,"passed_time":38.74749547,"remaining_time":48.52163847},
{"learn":[0.102288596],"iteration":444,"passed_time":38.81843798,"remaining_time":48.41400691},
{"learn":[0.1022095418],"iteration":445,"passed_time":38.88764604,"remaining_time":48.30438543},
{"learn":[0.1021878992],"iteration":446,"passed_time":38.95014752,"remaining_time":48.18664783},
{"learn":[0.1021533285],"iteration":447,"passed_time":39.01811297,"remaining_time":48.07588919},
{"learn":[0.1021346984],"iteration":448,"passed_time":39.08575288,"remaining_time":47.96492168},
{"learn":[0.1021134643],"iteration":449,"passed_time":39.15489709,"remaining_time":47.85598533},
{"learn":[0.1020862568],"iteration":450,"passed_time":39.22030491,"remaining_time":47.74267715},
{"learn":[0.1020622922],"iteration":451,"passed_time":39.28449797,"remaining_time":47.62810816},
{"learn":[0.1020374431],"iteration":452,"passed_time":39.34814261,"remaining_time":47.51309935},
{"learn":[0.1020098221],"iteration":453,"passed_time":39.41237027,"remaining_time":47.39901799},
{"learn":[0.1019934637],"iteration":454,"passed_time":39.4741816,"remaining_time":47.28226147},
{"learn":[0.1019834231],"iteration":455,"passed_time":39.54144585,"remaining_time":47.17225119},
{"learn":[0.1019455419],"iteration":456,"passed_time":39.60879925,"remaining_time":47.06253391},
{"learn":[0.1018894768],"iteration":457,"passed_time":39.67536132,"remaining_time":46.95206514},
{"learn":[0.1018684611],"iteration":458,"passed_time":39.73916667,"remaining_time":46.83853849},
{"learn":[0.1018373057],"iteration":459,"passed_time":39.80500769,"remaining_time":46.72761772},
{"learn":[0.1018178079],"iteration":460,"passed_time":39.87304818,"remaining_time":46.61946414},
{"learn":[0.1017888815],"iteration":461,"passed_time":39.93680116,"remaining_time":46.50649139},
{"learn":[0.1017608986],"iteration":462,"passed_time":40.00187004,"remaining_time":46.39525747},
{"learn":[0.1016587234],"iteration":463,"passed_time":40.07255924,"remaining_time":46.29071498},
{"learn":[0.1016327929],"iteration":464,"passed_time":40.13750985,"remaining_time":46.17971563},
{"learn":[0.1016100457],"iteration":465,"passed_time":40.20363868,"remaining_time":46.07026407},
{"learn":[0.1015924442],"iteration":466,"passed_time":40.26562398,"remaining_time":45.95626892},
{"learn":[0.1015657068],"iteration":467,"passed_time":40.33220283,"remaining_time":45.84771775},
{"learn":[0.1015493087],"iteration":468,"passed_time":40.39629436,"remaining_time":45.73652943},
{"learn":[0.1015288078],"iteration":469,"passed_time":40.4568806,"remaining_time":45.62158877},
{"learn":[0.1015135286],"iteration":470,"passed_time":40.51925039,"remaining_time":45.50888207},
{"learn":[0.1014939572],"iteration":471,"passed_time":40.58764329,"remaining_time":45.40312639},
{"learn":[0.1014775495],"iteration":472,"passed_time":40.64977126,"remaining_time":45.29054853},
{"learn":[0.1014526321],"iteration":473,"passed_time":40.71448959,"remaining_time":45.18105807},
{"learn":[0.1014358501],"iteration":474,"passed_time":40.77987838,"remaining_time":45.07249715},
{"learn":[0.1014110344],"iteration":475,"passed_time":40.84410389,"remaining_time":44.96283705},
{"learn":[0.1013743397],"iteration":476,"passed_time":40.91591437,"remaining_time":44.86168389},
{"learn":[0.1013523527],"iteration":477,"passed_time":40.98019183,"remaining_time":44.75242706},
{"learn":[0.1013039501],"iteration":478,"passed_time":41.04433339,"remaining_time":44.64321022},
{"learn":[0.1012748612],"iteration":479,"passed_time":41.1158439,"remaining_time":44.54216423},
{"learn":[0.1012475875],"iteration":480,"passed_time":41.18237896,"remaining_time":44.43587252},
{"learn":[0.1012327239],"iteration":481,"passed_time":41.25910702,"remaining_time":44.34070008},
{"learn":[0.1012029661],"iteration":482,"passed_time":41.32191275,"remaining_time":44.23070164},
{"learn":[0.1011690555],"iteration":483,"passed_time":41.38460327,"remaining_time":44.12077539},
{"learn":[0.1011439998],"iteration":484,"passed_time":41.44715199,"remaining_time":44.01089335},
{"learn":[0.1011212443],"iteration":485,"passed_time":41.51118256,"remaining_time":43.90277332},
{"learn":[0.1010950807],"iteration":486,"passed_time":41.57365753,"remaining_time":43.79319572},
{"learn":[0.101039034],"iteration":487,"passed_time":41.64447259,"remaining_time":43.69256141},
{"learn":[0.1010050288],"iteration":488,"passed_time":41.70876081,"remaining_time":43.58522857},
{"learn":[0.1009875449],"iteration":489,"passed_time":41.7733969,"remaining_time":43.47843351},
{"learn":[0.1009616149],"iteration":490,"passed_time":41.84600846,"remaining_time":43.38007802},
{"learn":[0.1009425734],"iteration":491,"passed_time":41.92220221,"remaining_time":43.28552586},
{"learn":[0.100925845],"iteration":492,"passed_time":42.00373481,"remaining_time":43.19653864},
{"learn":[0.100901783],"iteration":493,"passed_time":42.08303452,"remaining_time":43.10529447},
{"learn":[0.1008689081],"iteration":494,"passed_time":42.15705283,"remaining_time":43.00871046},
{"learn":[0.1008390535],"iteration":495,"passed_time":42.22648977,"remaining_time":42.90756219},
{"learn":[0.1008253819],"iteration":496,"passed_time":42.2980392,"remaining_time":42.80867951},
{"learn":[0.1008026146],"iteration":497,"passed_time":42.37126433,"remaining_time":42.71159577},
{"learn":[0.1007685963],"iteration":498,"passed_time":42.44972496,"remaining_time":42.61986414},
{"learn":[0.1007400199],"iteration":499,"passed_time":42.52148868,"remaining_time":42.52148868},
{"learn":[0.1007193152],"iteration":500,"passed_time":42.59295248,"remaining_time":42.42292073},
{"learn":[0.1006938924],"iteration":501,"passed_time":42.66427399,"remaining_time":42.32431962},
{"learn":[0.1006770284],"iteration":502,"passed_time":42.7308475,"remaining_time":42.2211356},
{"learn":[0.100650822],"iteration":503,"passed_time":42.80275098,"remaining_time":42.12334224},
{"learn":[0.1006256158],"iteration":504,"passed_time":42.87822128,"remaining_time":42.02914759},
{"learn":[0.1005981203],"iteration":505,"passed_time":42.95873591,"remaining_time":41.93995166},
{"learn":[0.1005780805],"iteration":506,"passed_time":43.03055847,"remaining_time":41.84233792},
{"learn":[0.1005549155],"iteration":507,"passed_time":43.10673463,"remaining_time":41.7490422},
{"learn":[0.1005296082],"iteration":508,"passed_time":43.19444829,"remaining_time":41.66694325},
{"learn":[0.1004962105],"iteration":509,"passed_time":43.27505462,"remaining_time":41.57799365},
{"learn":[0.1004680537],"iteration":510,"passed_time":43.34625497,"remaining_time":41.4800757},
{"learn":[0.1004457892],"iteration":511,"passed_time":43.42066804,"remaining_time":41.38532422},
{"learn":[0.1004183954],"iteration":512,"passed_time":43.48978474,"remaining_time":41.28562411},
{"learn":[0.1003967449],"iteration":513,"passed_time":43.56129221,"remaining_time":41.18830353},
{"learn":[0.1003677503],"iteration":514,"passed_time":43.63509424,"remaining_time":41.09324409},
{"learn":[0.1003337084],"iteration":515,"passed_time":43.71316499,"remaining_time":41.00227103},
{"learn":[0.100303864],"iteration":516,"passed_time":43.78287214,"remaining_time":40.90353432},
{"learn":[0.1002778789],"iteration":517,"passed_time":43.85952374,"remaining_time":40.81137151},
{"learn":[0.1002527444],"iteration":518,"passed_time":43.93041818,"remaining_time":40.71393284},
{"learn":[0.1002291793],"iteration":519,"passed_time":43.9947208,"remaining_time":40.61051151},
{"learn":[0.1002079044],"iteration":520,"passed_time":44.06200297,"remaining_time":40.5099797},
{"learn":[0.1001800915],"iteration":521,"passed_time":44.14421393,"remaining_time":40.42324571},
{"learn":[0.1001477537],"iteration":522,"passed_time":44.2158467,"remaining_time":40.32688122},
{"learn":[0.1001165354],"iteration":523,"passed_time":44.28165379,"remaining_time":40.22531909},
{"learn":[0.1000950921],"iteration":524,"passed_time":44.34784929,"remaining_time":40.1242446},
{"learn":[0.1000712194],"iteration":525,"passed_time":44.42045504,"remaining_time":40.02907926},
{"learn":[0.1000381534],"iteration":526,"passed_time":44.49484229,"remaining_time":39.93559848},
{"learn":[0.1000100033],"iteration":527,"passed_time":44.57247499,"remaining_time":39.84509128},
{"learn":[0.0999842392],"iteration":528,"passed_time":44.65128061,"remaining_time":39.75567707},
{"learn":[0.09991337489],"iteration":529,"passed_time":44.73006219,"remaining_time":39.66628157},
{"learn":[0.09989610416],"iteration":530,"passed_time":44.79991863,"remaining_time":39.56904301},
{"learn":[0.09987800126],"iteration":531,"passed_time":44.87192917,"remaining_time":39.47380236},
{"learn":[0.09986367827],"iteration":532,"passed_time":44.94072581,"remaining_time":39.37583294},
{"learn":[0.09984264474],"iteration":533,"passed_time":45.02707665,"remaining_time":39.29329161},
{"learn":[0.09982105398],"iteration":534,"passed_time":45.09590029,"remaining_time":39.19550212},
{"learn":[0.09979924214],"iteration":535,"passed_time":45.16749825,"remaining_time":39.10022237},
{"learn":[0.09978630121],"iteration":536,"passed_time":45.24037817,"remaining_time":39.00613612},
{"learn":[0.09976450361],"iteration":537,"passed_time":45.31116873,"remaining_time":38.91033449},
{"learn":[0.09974693128],"iteration":538,"passed_time":45.38762655,"remaining_time":38.8194728},
{"learn":[0.09973061087],"iteration":539,"passed_time":45.45951799,"remaining_time":38.72477458},
{"learn":[0.0997090183],"iteration":540,"passed_time":45.53644013,"remaining_time":38.63442887},
{"learn":[0.09968945689],"iteration":541,"passed_time":45.61302115,"remaining_time":38.54384444},
{"learn":[0.09966470058],"iteration":542,"passed_time":45.68767873,"remaining_time":38.45169278},
{"learn":[0.09962081234],"iteration":543,"passed_time":45.76295003,"remaining_time":38.36011988},
{"learn":[0.09958566653],"iteration":544,"passed_time":45.83479688,"remaining_time":38.26574785},
{"learn":[0.09955801864],"iteration":545,"passed_time":45.91270432,"remaining_time":38.17649773},
{"learn":[0.09953913005],"iteration":546,"passed_time":45.98879443,"remaining_time":38.08578405},
{"learn":[0.09952175397],"iteration":547,"passed_time":46.07452124,"remaining_time":38.00307226},
{"learn":[0.09949130834],"iteration":548,"passed_time":46.14553708,"remaining_time":37.90826452},
{"learn":[0.09946379188],"iteration":549,"passed_time":46.22555046,"remaining_time":37.82090492},
{"learn":[0.09939846114],"iteration":550,"passed_time":46.31340355,"remaining_time":37.73996042},
{"learn":[0.09937262794],"iteration":551,"passed_time":46.37885883,"remaining_time":37.64081297},
{"learn":[0.09933530687],"iteration":552,"passed_time":46.4433487,"remaining_time":37.541007},
{"learn":[0.09931651065],"iteration":553,"passed_time":46.51063372,"remaining_time":37.44357877},
{"learn":[0.09928706503],"iteration":554,"passed_time":46.58156217,"remaining_time":37.34918048},
{"learn":[0.09926314625],"iteration":555,"passed_time":46.64916356,"remaining_time":37.25220975},
{"learn":[0.09923699608],"iteration":556,"passed_time":46.72091062,"remaining_time":37.15864166},
{"learn":[0.09921530791],"iteration":557,"passed_time":46.78629621,"remaining_time":37.06011277},
{"learn":[0.09919133128],"iteration":558,"passed_time":46.85166805,"remaining_time":36.96169161},
{"learn":[0.09916724404],"iteration":559,"passed_time":46.91531973,"remaining_time":36.86203693},
{"learn":[0.09914414824],"iteration":560,"passed_time":46.98315537,"remaining_time":36.76578468},
{"learn":[0.0991236812],"iteration":561,"passed_time":47.04957591,"remaining_time":36.66853069},
{"learn":[0.09910636257],"iteration":562,"passed_time":47.11482918,"remaining_time":36.5704802},
{"learn":[0.0990887557],"iteration":563,"passed_time":47.18418711,"remaining_time":36.47571911},
{"learn":[0.0990508045],"iteration":564,"passed_time":47.24967745,"remaining_time":36.37807025},
{"learn":[0.09903501761],"iteration":565,"passed_time":47.31636503,"remaining_time":36.28145304},
{"learn":[0.09900880205],"iteration":566,"passed_time":47.38700372,"remaining_time":36.18795875},
{"learn":[0.09899094586],"iteration":567,"passed_time":47.45123057,"remaining_time":36.08966832},
{"learn":[0.09896600388],"iteration":568,"passed_time":47.51617113,"remaining_time":35.99203823},
{"learn":[0.09894666335],"iteration":569,"passed_time":47.58463482,"remaining_time":35.89718065},
{"learn":[0.09891623319],"iteration":570,"passed_time":47.65385578,"remaining_time":35.80298447},
{"learn":[0.09889871056],"iteration":571,"passed_time":47.71676351,"remaining_time":35.70415172},
{"learn":[0.09887570295],"iteration":572,"passed_time":47.7872195,"remaining_time":35.61106933},
{"learn":[0.09885785315],"iteration":573,"passed_time":47.85331143,"remaining_time":35.51482695},
{"learn":[0.09883883572],"iteration":574,"passed_time":47.93112234,"remaining_time":35.42735129},
{"learn":[0.09880197916],"iteration":575,"passed_time":48.02011411,"remaining_time":35.34813956},
{"learn":[0.09878092273],"iteration":576,"passed_time":48.1002613,"remaining_time":35.26240993},
{"learn":[0.09872482266],"iteration":577,"passed_time":48.17541453,"remaining_time":35.17305351},
{"learn":[0.09870310326],"iteration":578,"passed_time":48.25989793,"remaining_time":35.09053028},
{"learn":[0.09868261883],"iteration":579,"passed_time":48.34334682,"remaining_time":35.00725114},
{"learn":[0.09865623675],"iteration":580,"passed_time":48.43231536,"remaining_time":34.92795204},
{"learn":[0.09863827658],"iteration":581,"passed_time":48.4945486,"remaining_time":34.82941807},
{"learn":[0.09860761228],"iteration":582,"passed_time":48.55925338,"remaining_time":34.73277643},
{"learn":[0.0985914184],"iteration":583,"passed_time":48.61885254,"remaining_time":34.63260729},
{"learn":[0.09854210443],"iteration":584,"passed_time":48.6849659,"remaining_time":34.53719803},
{"learn":[0.09852438809],"iteration":585,"passed_time":48.74464742,"remaining_time":34.43734477},
{"learn":[0.09849509249],"iteration":586,"passed_time":48.81165354,"remaining_time":34.3427818},
{"learn":[0.09846986551],"iteration":587,"passed_time":48.87706376,"remaining_time":34.24719434},
{"learn":[0.09844460739],"iteration":588,"passed_time":48.94130185,"remaining_time":34.15089145},
{"learn":[0.09842940908],"iteration":589,"passed_time":49.00629023,"remaining_time":34.05521863},
{"learn":[0.09839726481],"iteration":590,"passed_time":49.07632546,"remaining_time":33.96314233},
{"learn":[0.09837378999],"iteration":591,"passed_time":49.13802602,"remaining_time":33.86539631},
{"learn":[0.0983426495],"iteration":592,"passed_time":49.20864824,"remaining_time":33.77389517},
{"learn":[0.0983327356],"iteration":593,"passed_time":49.27446703,"remaining_time":33.67918117},
{"learn":[0.09830992],"iteration":594,"passed_time":49.33733562,"remaining_time":33.58255618},
{"learn":[0.09828401842],"iteration":595,"passed_time":49.40621681,"remaining_time":33.49012012},
{"learn":[0.09826226363],"iteration":596,"passed_time":49.46824028,"remaining_time":33.39313372},
{"learn":[0.09824098766],"iteration":597,"passed_time":49.53590725,"remaining_time":33.30005805},
{"learn":[0.09822721923],"iteration":598,"passed_time":49.59696461,"remaining_time":33.20264242},
{"learn":[0.09819695136],"iteration":599,"passed_time":49.66649184,"remaining_time":33.11099456},
{"learn":[0.09817942525],"iteration":600,"passed_time":49.73235326,"remaining_time":33.01698661},
{"learn":[0.09814623584],"iteration":601,"passed_time":49.79475901,"remaining_time":32.92078752},
{"learn":[0.09812680287],"iteration":602,"passed_time":49.86610334,"remaining_time":32.83058545},
{"learn":[0.09810811514],"iteration":603,"passed_time":49.9292569,"remaining_time":32.73507572},
{"learn":[0.09808718985],"iteration":604,"passed_time":49.99186184,"remaining_time":32.63931475},
{"learn":[0.098061158],"iteration":605,"passed_time":50.05701033,"remaining_time":32.54531695},
{"learn":[0.09787502936],"iteration":606,"passed_time":50.12999553,"remaining_time":32.45648804},
{"learn":[0.09779790639],"iteration":607,"passed_time":50.20512823,"remaining_time":32.36909583},
{"learn":[0.09776359799],"iteration":608,"passed_time":50.27357779,"remaining_time":32.27745307},
{"learn":[0.09774881375],"iteration":609,"passed_time":50.33535278,"remaining_time":32.18161899},
{"learn":[0.09772623717],"iteration":610,"passed_time":50.40318653,"remaining_time":32.08975378},
{"learn":[0.09770319173],"iteration":611,"passed_time":50.46764974,"remaining_time":31.99583023},
{"learn":[0.09768457521],"iteration":612,"passed_time":50.53759163,"remaining_time":31.9054616},
{"learn":[0.09766018406],"iteration":613,"passed_time":50.60620558,"remaining_time":31.81432468},
{"learn":[0.09762951672],"iteration":614,"passed_time":50.67240406,"remaining_time":31.72174888},
{"learn":[0.09760846544],"iteration":615,"passed_time":50.7358852,"remaining_time":31.6275648},
{"learn":[0.09758068098],"iteration":616,"passed_time":50.80650154,"remaining_time":31.53790938},
{"learn":[0.09755330569],"iteration":617,"passed_time":50.88196781,"remaining_time":31.45131344},
{"learn":[0.0975274374],"iteration":618,"passed_time":50.94852342,"remaining_time":31.35926886},
{"learn":[0.09750966383],"iteration":619,"passed_time":51.01256864,"remaining_time":31.26576788},
{"learn":[0.09748416314],"iteration":620,"passed_time":51.07971198,"remaining_time":31.17425256},
{"learn":[0.09746848785],"iteration":621,"passed_time":51.13904193,"remaining_time":31.07806728},
{"learn":[0.09744566344],"iteration":622,"passed_time":51.20269577,"remaining_time":30.98461686},
{"learn":[0.09741477959],"iteration":623,"passed_time":51.27835206,"remaining_time":30.89849419},
{"learn":[0.09739834498],"iteration":624,"passed_time":51.35085272,"remaining_time":30.81051163},
{"learn":[0.09737139527],"iteration":625,"passed_time":51.41738201,"remaining_time":30.71901098},
{"learn":[0.09734774356],"iteration":626,"passed_time":51.48480728,"remaining_time":30.62812299},
{"learn":[0.09732162636],"iteration":627,"passed_time":51.5501201,"remaining_time":30.5360584},
{"learn":[0.09728686528],"iteration":628,"passed_time":51.62566604,"remaining_time":30.45011463},
{"learn":[0.0972462128],"iteration":629,"passed_time":51.69244068,"remaining_time":30.35905247},
{"learn":[0.09723571624],"iteration":630,"passed_time":51.75641411,"remaining_time":30.26642917},
{"learn":[0.09720466686],"iteration":631,"passed_time":51.82536236,"remaining_time":30.17679327},
{"learn":[0.09718508216],"iteration":632,"passed_time":51.89444677,"remaining_time":30.08730168},
{"learn":[0.0971712511],"iteration":633,"passed_time":51.95691884,"remaining_time":29.99405725},
{"learn":[0.0971541229],"iteration":634,"passed_time":52.01744932,"remaining_time":29.8997937},
{"learn":[0.09712796351],"iteration":635,"passed_time":52.08312705,"remaining_time":29.80858215},
{"learn":[0.09709433601],"iteration":636,"passed_time":52.15440053,"remaining_time":29.72063955},
{"learn":[0.09706982275],"iteration":637,"passed_time":52.22194212,"remaining_time":29.63063174},
{"learn":[0.09703728522],"iteration":638,"passed_time":52.2888666,"remaining_time":29.54034561},
{"learn":[0.09701266639],"iteration":639,"passed_time":52.35491885,"remaining_time":29.44964185},
{"learn":[0.09698202351],"iteration":640,"passed_time":52.43121767,"remaining_time":29.36475373},
{"learn":[0.09696767233],"iteration":641,"passed_time":52.49927452,"remaining_time":29.27529638},
{"learn":[0.0969453017],"iteration":642,"passed_time":52.56814692,"remaining_time":29.1863584},
{"learn":[0.09692851982],"iteration":643,"passed_time":52.63484037,"remaining_time":29.09627822},
{"learn":[0.09690223977],"iteration":644,"passed_time":52.70528281,"remaining_time":29.00833395},
{"learn":[0.09686779632],"iteration":645,"passed_time":52.77146819,"remaining_time":28.91811105},
{"learn":[0.09684698093],"iteration":646,"passed_time":52.83751446,"remaining_time":28.82788656},
{"learn":[0.09683493571],"iteration":647,"passed_time":52.90690635,"remaining_time":28.73955407},
{"learn":[0.09680874365],"iteration":648,"passed_time":52.97677619,"remaining_time":28.65153843},
{"learn":[0.0967814504],"iteration":649,"passed_time":53.04627852,"remaining_time":28.56338074},
{"learn":[0.09676088471],"iteration":650,"passed_time":53.11396856,"remaining_time":28.4743088},
{"learn":[0.09674334244],"iteration":651,"passed_time":53.17862553,"remaining_time":28.38368357},
{"learn":[0.09671872045],"iteration":652,"passed_time":53.24075353,"remaining_time":28.29179399},
{"learn":[0.09669342534],"iteration":653,"passed_time":53.30015915,"remaining_time":28.19855515},
{"learn":[0.09667676073],"iteration":654,"passed_time":53.37208278,"remaining_time":28.11201307},
{"learn":[0.09666297368],"iteration":655,"passed_time":53.43998005,"remaining_time":28.02340417},
{"learn":[0.09664261725],"iteration":656,"passed_time":53.50523643,"remaining_time":27.9334796},
{"learn":[0.0966153646],"iteration":657,"passed_time":53.56843963,"remaining_time":27.84256285},
{"learn":[0.09658993948],"iteration":658,"passed_time":53.64116487,"remaining_time":27.75665739},
{"learn":[0.09656277119],"iteration":659,"passed_time":53.71813225,"remaining_time":27.67297722},
{"learn":[0.09654655384],"iteration":660,"passed_time":53.79463846,"remaining_time":27.58908084},
{"learn":[0.09653388633],"iteration":661,"passed_time":53.88077042,"remaining_time":27.51012146},
{"learn":[0.09651735717],"iteration":662,"passed_time":53.96073017,"remaining_time":27.42800312},
{"learn":[0.09648361044],"iteration":663,"passed_time":54.02759523,"remaining_time":27.33926505},
{"learn":[0.09647446424],"iteration":664,"passed_time":54.08827449,"remaining_time":27.24747662},
{"learn":[0.09644694695],"iteration":665,"passed_time":54.15353374,"remaining_time":27.15807848},
{"learn":[0.09642366792],"iteration":666,"passed_time":54.21860673,"remaining_time":27.06865973},
{"learn":[0.09640024242],"iteration":667,"passed_time":54.2812461,"remaining_time":26.97810435},
{"learn":[0.09637554197],"iteration":668,"passed_time":54.34311459,"remaining_time":26.88725102},
{"learn":[0.09635388656],"iteration":669,"passed_time":54.40534488,"remaining_time":26.7966624},
{"learn":[0.09632316984],"iteration":670,"passed_time":54.47183784,"remaining_time":26.70824836},
{"learn":[0.09630740607],"iteration":671,"passed_time":54.53725496,"remaining_time":26.61937444},
{"learn":[0.09628875974],"iteration":672,"passed_time":54.60145801,"remaining_time":26.52998034},
{"learn":[0.09627522483],"iteration":673,"passed_time":54.66212307,"remaining_time":26.43894974},
{"learn":[0.09626266162],"iteration":674,"passed_time":54.72453238,"remaining_time":26.34884892},
{"learn":[0.09624156841],"iteration":675,"passed_time":54.78823568,"remaining_time":26.25945023},
{"learn":[0.09611159458],"iteration":676,"passed_time":54.8711558,"remaining_time":26.1792959},
{"learn":[0.09609254914],"iteration":677,"passed_time":54.93477639,"remaining_time":26.08996755},
{"learn":[0.0960504325],"iteration":678,"passed_time":54.99376719,"remaining_time":25.99852617},
{"learn":[0.09603247957],"iteration":679,"passed_time":55.07084873,"remaining_time":25.91569352},
{"learn":[0.09601251187],"iteration":680,"passed_time":55.14599118,"remaining_time":25.83196944},
{"learn":[0.09597739004],"iteration":681,"passed_time":55.21226544,"remaining_time":25.7441355},
{"learn":[0.09594303167],"iteration":682,"passed_time":55.27740838,"remaining_time":25.65583961},
{"learn":[0.09575936372],"iteration":683,"passed_time":55.35275221,"remaining_time":25.57232412},
{"learn":[0.095744692],"iteration":684,"passed_time":55.41887063,"remaining_time":25.48459015},
{"learn":[0.09572717762],"iteration":685,"passed_time":55.49358124,"remaining_time":25.40085205},
{"learn":[0.09570165946],"iteration":686,"passed_time":55.55903633,"remaining_time":25.31292339},
{"learn":[0.09568253175],"iteration":687,"passed_time":55.62494442,"remaining_time":25.22526549},
{"learn":[0.09565689913],"iteration":688,"passed_time":55.69184327,"remaining_time":25.13811794},
{"learn":[0.09563985366],"iteration":689,"passed_time":55.75578925,"remaining_time":25.04970242},
{"learn":[0.09562874391],"iteration":690,"passed_time":55.81884437,"remaining_time":24.96095935},
{"learn":[0.09560722766],"iteration":691,"passed_time":55.88651618,"remaining_time":24.87434535},
{"learn":[0.09558513186],"iteration":692,"passed_time":55.95350004,"remaining_time":24.78748126},
{"learn":[0.09556328493],"iteration":693,"passed_time":56.01272631,"remaining_time":24.69725396},
{"learn":[0.09553038271],"iteration":694,"passed_time":56.08340035,"remaining_time":24.61213972},
{"learn":[0.09550025991],"iteration":695,"passed_time":56.14887122,"remaining_time":24.52479433},
{"learn":[0.09547276706],"iteration":696,"passed_time":56.21544421,"remaining_time":24.43799081},
{"learn":[0.09545059397],"iteration":697,"passed_time":56.312906,"remaining_time":24.36460976},
{"learn":[0.09543246845],"iteration":698,"passed_time":56.37329282,"remaining_time":24.27519476},
{"learn":[0.09541712357],"iteration":699,"passed_time":56.43399979,"remaining_time":24.18599991},
{"learn":[0.09539184672],"iteration":700,"passed_time":56.50105283,"remaining_time":24.09959315},
{"learn":[0.09536706033],"iteration":701,"passed_time":56.56658592,"remaining_time":24.0125963},
{"learn":[0.09534551498],"iteration":702,"passed_time":56.63802917,"remaining_time":23.92815742},
{"learn":[0.09532761335],"iteration":703,"passed_time":56.70272585,"remaining_time":23.84091882},
{"learn":[0.09531287256],"iteration":704,"passed_time":56.76648479,"remaining_time":23.75335179},
{"learn":[0.09529320966],"iteration":705,"passed_time":56.83818603,"remaining_time":23.66915962},
{"learn":[0.09526908382],"iteration":706,"passed_time":56.90354777,"remaining_time":23.58237552},
{"learn":[0.09524162687],"iteration":707,"passed_time":56.97325651,"remaining_time":23.49744478},
{"learn":[0.09516903701],"iteration":708,"passed_time":57.04004928,"remaining_time":23.41136014},
{"learn":[0.09514757222],"iteration":709,"passed_time":57.10426562,"remaining_time":23.32427751},
{"learn":[0.09511180855],"iteration":710,"passed_time":57.18040993,"remaining_time":23.24210755},
{"learn":[0.09508883735],"iteration":711,"passed_time":57.24319599,"remaining_time":23.15455119},
{"learn":[0.09506989809],"iteration":712,"passed_time":57.30710487,"remaining_time":23.06751627},
{"learn":[0.09505139713],"iteration":713,"passed_time":57.37319604,"remaining_time":22.98142026},
{"learn":[0.09502834279],"iteration":714,"passed_time":57.4380103,"remaining_time":22.89487124},
{"learn":[0.09500424838],"iteration":715,"passed_time":57.5053417,"remaining_time":22.80938134},
{"learn":[0.09498189],"iteration":716,"passed_time":57.57074053,"remaining_time":22.72317932},
{"learn":[0.09495615379],"iteration":717,"passed_time":57.63950245,"remaining_time":22.63835612},
{"learn":[0.09493334476],"iteration":718,"passed_time":57.71474624,"remaining_time":22.55611084},
{"learn":[0.0949146771],"iteration":719,"passed_time":57.77666028,"remaining_time":22.46870122},
{"learn":[0.09489185018],"iteration":720,"passed_time":57.84040478,"remaining_time":22.38207064},
{"learn":[0.09486857761],"iteration":721,"passed_time":57.92185188,"remaining_time":22.3023197},
{"learn":[0.09485572434],"iteration":722,"passed_time":58.00012817,"remaining_time":22.22134924},
{"learn":[0.09483204087],"iteration":723,"passed_time":58.07074664,"remaining_time":22.13746695},
{"learn":[0.09481189033],"iteration":724,"passed_time":58.13946733,"remaining_time":22.0529014},
{"learn":[0.09479534705],"iteration":725,"passed_time":58.21412872,"remaining_time":21.97062158},
{"learn":[0.09477336552],"iteration":726,"passed_time":58.28611026,"remaining_time":21.8873564},
{"learn":[0.09474116753],"iteration":727,"passed_time":58.35992361,"remaining_time":21.80480662},
{"learn":[0.09472604667],"iteration":728,"passed_time":58.43956769,"remaining_time":21.72444835},
{"learn":[0.09469695933],"iteration":729,"passed_time":58.51428054,"remaining_time":21.64226814},
{"learn":[0.09467521484],"iteration":730,"passed_time":58.58702217,"remaining_time":21.55938299},
{"learn":[0.09465837423],"iteration":731,"passed_time":58.65617446,"remaining_time":21.47521142},
{"learn":[0.09464379948],"iteration":732,"passed_time":58.72841851,"remaining_time":21.39220701},
{"learn":[0.09462165353],"iteration":733,"passed_time":58.81037002,"remaining_time":21.3127499},
{"learn":[0.09460170694],"iteration":734,"passed_time":58.88762847,"remaining_time":21.23159394},
{"learn":[0.09458346318],"iteration":735,"passed_time":58.95916911,"remaining_time":21.14839762},
{"learn":[0.09454488608],"iteration":736,"passed_time":59.03685942,"remaining_time":21.06742745},
{"learn":[0.0945038531],"iteration":737,"passed_time":59.12348195,"remaining_time":20.98963722},
{"learn":[0.09449283768],"iteration":738,"passed_time":59.20639351,"remaining_time":20.91051246},
{"learn":[0.09445694184],"iteration":739,"passed_time":59.27643061,"remaining_time":20.826854},
{"learn":[0.09442951098],"iteration":740,"passed_time":59.35399214,"remaining_time":20.7458623},
{"learn":[0.09440534146],"iteration":741,"passed_time":59.42470572,"remaining_time":20.66249875},
{"learn":[0.09438924406],"iteration":742,"passed_time":59.4965344,"remaining_time":20.57955497},
{"learn":[0.09436789516],"iteration":743,"passed_time":59.57255685,"remaining_time":20.49808408},
{"learn":[0.09434254297],"iteration":744,"passed_time":59.65811952,"remaining_time":20.41989326},
{"learn":[0.09431829602],"iteration":745,"passed_time":59.73233723,"remaining_time":20.33781992},
{"learn":[0.09429900365],"iteration":746,"passed_time":59.79901699,"remaining_time":20.25321459},
{"learn":[0.09427283592],"iteration":747,"passed_time":59.87028924,"remaining_time":20.1702044},
{"learn":[0.09425790921],"iteration":748,"passed_time":59.93728443,"remaining_time":20.08579224},
{"learn":[0.09422839377],"iteration":749,"passed_time":60.02321824,"remaining_time":20.00773941},
{"learn":[0.09421659495],"iteration":750,"passed_time":60.09565438,"remaining_time":19.92519034},
{"learn":[0.09420185374],"iteration":751,"passed_time":60.16222062,"remaining_time":19.84073233},
{"learn":[0.09418194462],"iteration":752,"passed_time":60.23377238,"remaining_time":19.75795721},
{"learn":[0.09415494607],"iteration":753,"passed_time":60.30215415,"remaining_time":19.67417761},
{"learn":[0.09413869035],"iteration":754,"passed_time":60.38187918,"remaining_time":19.59411974},
{"learn":[0.09412197483],"iteration":755,"passed_time":60.45338534,"remaining_time":19.51141008},
{"learn":[0.09410458373],"iteration":756,"passed_time":60.52154789,"remaining_time":19.42765672},
{"learn":[0.09408351057],"iteration":757,"passed_time":60.5983347,"remaining_time":19.34669789},
{"learn":[0.09406581109],"iteration":758,"passed_time":60.66616671,"remaining_time":19.26290669},
{"learn":[0.09404843051],"iteration":759,"passed_time":60.739072,"remaining_time":19.18075958},
{"learn":[0.09403808285],"iteration":760,"passed_time":60.80521588,"remaining_time":19.09651327},
{"learn":[0.09401899277],"iteration":761,"passed_time":60.88683894,"remaining_time":19.01714917},
{"learn":[0.09400294477],"iteration":762,"passed_time":60.96804119,"remaining_time":18.93764844},
{"learn":[0.09398019124],"iteration":763,"passed_time":61.04393625,"remaining_time":18.85650387},
{"learn":[0.09396461291],"iteration":764,"passed_time":61.11462766,"remaining_time":18.77377451},
{"learn":[0.09394020972],"iteration":765,"passed_time":61.18634784,"remaining_time":18.69139086},
{"learn":[0.09391824726],"iteration":766,"passed_time":61.26472135,"remaining_time":18.61105616},
{"learn":[0.09388597272],"iteration":767,"passed_time":61.34475786,"remaining_time":18.53122894},
{"learn":[0.09386867986],"iteration":768,"passed_time":61.42907578,"remaining_time":18.45268726},
{"learn":[0.09385108176],"iteration":769,"passed_time":61.50850307,"remaining_time":18.37266975},
{"learn":[0.09383286454],"iteration":770,"passed_time":61.57711432,"remaining_time":18.28944122},
{"learn":[0.09380205291],"iteration":771,"passed_time":61.65204742,"remaining_time":18.20811763},
{"learn":[0.09378014192],"iteration":772,"passed_time":61.7228839,"remaining_time":18.12560756},
{"learn":[0.09375677532],"iteration":773,"passed_time":61.80435736,"remaining_time":18.04623355},
{"learn":[0.09374161357],"iteration":774,"passed_time":61.87801757,"remaining_time":17.96458575},
{"learn":[0.09372614388],"iteration":775,"passed_time":61.96147492,"remaining_time":17.88578657},
{"learn":[0.09369254386],"iteration":776,"passed_time":62.03816709,"remaining_time":17.8050338},
{"learn":[0.09366757088],"iteration":777,"passed_time":62.12244371,"remaining_time":17.72645566},
{"learn":[0.09363779852],"iteration":778,"passed_time":62.20722724,"remaining_time":17.6480067},
{"learn":[0.09360605566],"iteration":779,"passed_time":62.28067884,"remaining_time":17.56634531},
{"learn":[0.09357843498],"iteration":780,"passed_time":62.35832642,"remaining_time":17.48588154},
{"learn":[0.09355263648],"iteration":781,"passed_time":62.43714474,"remaining_time":17.40575135},
{"learn":[0.09353630646],"iteration":782,"passed_time":62.50705759,"remaining_time":17.32315645},
{"learn":[0.09351775358],"iteration":783,"passed_time":62.5714897,"remaining_time":17.2390839},
{"learn":[0.0934980835],"iteration":784,"passed_time":62.64065899,"remaining_time":17.15635883},
{"learn":[0.09346672283],"iteration":785,"passed_time":62.71078801,"remaining_time":17.07392956},
{"learn":[0.09344048256],"iteration":786,"passed_time":62.77434005,"remaining_time":16.9897515},
{"learn":[0.0934263496],"iteration":787,"passed_time":62.84098179,"remaining_time":16.90645703},
{"learn":[0.09335018234],"iteration":788,"passed_time":62.90933928,"remaining_time":16.82366361},
{"learn":[0.09331157584],"iteration":789,"passed_time":62.97489899,"remaining_time":16.74016302},
{"learn":[0.09329102598],"iteration":790,"passed_time":63.04830772,"remaining_time":16.65878168},
{"learn":[0.09327067537],"iteration":791,"passed_time":63.12048269,"remaining_time":16.57709647},
{"learn":[0.09324989761],"iteration":792,"passed_time":63.18408115,"remaining_time":16.49319647},
{"learn":[0.09323327341],"iteration":793,"passed_time":63.24802818,"remaining_time":16.40943804},
{"learn":[0.09321359528],"iteration":794,"passed_time":63.3097695,"remaining_time":16.32516069},
{"learn":[0.0931779505],"iteration":795,"passed_time":63.37814908,"remaining_time":16.24264122},
{"learn":[0.09315944888],"iteration":796,"passed_time":63.44754957,"remaining_time":16.16041727},
{"learn":[0.09313911091],"iteration":797,"passed_time":63.52890372,"remaining_time":16.08125132},
{"learn":[0.09312677558],"iteration":798,"passed_time":63.59618789,"remaining_time":15.99854038},
{"learn":[0.09311636812],"iteration":799,"passed_time":63.66224321,"remaining_time":15.9155608},
{"learn":[0.09310273452],"iteration":800,"passed_time":63.72911878,"remaining_time":15.83282726},
{"learn":[0.09308996012],"iteration":801,"passed_time":63.79809601,"remaining_time":15.75065213},
{"learn":[0.09306583508],"iteration":802,"passed_time":63.86882971,"remaining_time":15.66894079},
{"learn":[0.09304528696],"iteration":803,"passed_time":63.94385814,"remaining_time":15.58830372},
{"learn":[0.09302925863],"iteration":804,"passed_time":64.02030753,"remaining_time":15.5080248},
{"learn":[0.092998655],"iteration":805,"passed_time":64.09146731,"remaining_time":15.42648221},
{"learn":[0.09297869566],"iteration":806,"passed_time":64.16077739,"remaining_time":15.34452297},
{"learn":[0.09296515854],"iteration":807,"passed_time":64.22829865,"remaining_time":15.26216998},
{"learn":[0.09295030294],"iteration":808,"passed_time":64.29377848,"remaining_time":15.17937168},
{"learn":[0.09293902504],"iteration":809,"passed_time":64.35995822,"remaining_time":15.09678032},
{"learn":[0.09292129272],"iteration":810,"passed_time":64.42617764,"remaining_time":15.01423869},
{"learn":[0.09290291431],"iteration":811,"passed_time":64.49323192,"remaining_time":14.93193054},
{"learn":[0.09287618844],"iteration":812,"passed_time":64.56961382,"remaining_time":14.85180539},
{"learn":[0.09283950498],"iteration":813,"passed_time":64.6445453,"remaining_time":14.77135802},
{"learn":[0.09282891334],"iteration":814,"passed_time":64.71123981,"remaining_time":14.68905444},
{"learn":[0.09280888345],"iteration":815,"passed_time":64.78422716,"remaining_time":14.60820808},
{"learn":[0.09279219357],"iteration":816,"passed_time":64.85131447,"remaining_time":14.52605942},
{"learn":[0.09277755932],"iteration":817,"passed_time":64.91857121,"remaining_time":14.44398528},
{"learn":[0.09276402386],"iteration":818,"passed_time":64.98882942,"remaining_time":14.36261065},
{"learn":[0.09274085873],"iteration":819,"passed_time":65.06386753,"remaining_time":14.28231238},
{"learn":[0.09272734659],"iteration":820,"passed_time":65.12828864,"remaining_time":14.19971214},
{"learn":[0.09270474076],"iteration":821,"passed_time":65.20622723,"remaining_time":14.12008327},
{"learn":[0.09268665961],"iteration":822,"passed_time":65.26782734,"remaining_time":14.03694464},
{"learn":[0.09266892955],"iteration":823,"passed_time":65.33749903,"remaining_time":13.95558232},
{"learn":[0.09264208793],"iteration":824,"passed_time":65.41228104,"remaining_time":13.87533234},
{"learn":[0.0926308785],"iteration":825,"passed_time":65.48402449,"remaining_time":13.79445552},
{"learn":[0.09261202086],"iteration":826,"passed_time":65.55507935,"remaining_time":13.71345674},
{"learn":[0.09259005849],"iteration":827,"passed_time":65.63161848,"remaining_time":13.63362123},
{"learn":[0.09256535303],"iteration":828,"passed_time":65.70440502,"remaining_time":13.55301961},
{"learn":[0.09253600808],"iteration":829,"passed_time":65.77501011,"remaining_time":13.47199002},
{"learn":[0.09250907535],"iteration":830,"passed_time":65.84326186,"remaining_time":13.39050692},
{"learn":[0.09249913759],"iteration":831,"passed_time":65.91209862,"remaining_time":13.30917376},
{"learn":[0.09248531342],"iteration":832,"passed_time":65.98597825,"remaining_time":13.22888159},
{"learn":[0.09246642837],"iteration":833,"passed_time":66.06045624,"remaining_time":13.1487239},
{"learn":[0.09245223701],"iteration":834,"passed_time":66.12555541,"remaining_time":13.06672652},
{"learn":[0.09242893122],"iteration":835,"passed_time":66.1922709,"remaining_time":12.98508664},
{"learn":[0.09241868615],"iteration":836,"passed_time":66.25974971,"remaining_time":12.90363107},
{"learn":[0.09239049142],"iteration":837,"passed_time":66.32858359,"remaining_time":12.82247081},
{"learn":[0.0923711119],"iteration":838,"passed_time":66.39521624,"remaining_time":12.74091754},
{"learn":[0.09235218074],"iteration":839,"passed_time":66.46992471,"remaining_time":12.66093804},
{"learn":[0.09232652178],"iteration":840,"passed_time":66.53518397,"remaining_time":12.5791846},
{"learn":[0.09229887626],"iteration":841,"passed_time":66.60321034,"remaining_time":12.49798959},
{"learn":[0.09228113163],"iteration":842,"passed_time":66.6740476,"remaining_time":12.41734932},
{"learn":[0.09226706279],"iteration":843,"passed_time":66.7609711,"remaining_time":12.33970556},
{"learn":[0.09224827575],"iteration":844,"passed_time":66.82428096,"remaining_time":12.25770834},
{"learn":[0.09222466366],"iteration":845,"passed_time":66.89299931,"remaining_time":12.17673983},
{"learn":[0.09220315676],"iteration":846,"passed_time":66.95289759,"remaining_time":12.094207},
{"learn":[0.09219120356],"iteration":847,"passed_time":67.01957438,"remaining_time":12.01294258},
{"learn":[0.09217620952],"iteration":848,"passed_time":67.08392708,"remaining_time":11.93129916},
{"learn":[0.09216228882],"iteration":849,"passed_time":67.14851868,"remaining_time":11.84973859},
{"learn":[0.09214920832],"iteration":850,"passed_time":67.21603813,"remaining_time":11.76873053},
{"learn":[0.09213231307],"iteration":851,"passed_time":67.28329234,"remaining_time":11.68770806},
{"learn":[0.09211897366],"iteration":852,"passed_time":67.34457379,"remaining_time":11.60568857},
{"learn":[0.09209299274],"iteration":853,"passed_time":67.41448264,"remaining_time":11.52519258},
{"learn":[0.09206787626],"iteration":854,"passed_time":67.47865179,"remaining_time":11.44374796},
{"learn":[0.09204536364],"iteration":855,"passed_time":67.54599962,"remaining_time":11.36287844},
{"learn":[0.09202061411],"iteration":856,"passed_time":67.61252621,"remaining_time":11.28190344},
{"learn":[0.09200500742],"iteration":857,"passed_time":67.67957739,"remaining_time":11.20104894},
{"learn":[0.09198600245],"iteration":858,"passed_time":67.73931689,"remaining_time":11.11902641},
{"learn":[0.09196750172],"iteration":859,"passed_time":67.80889436,"remaining_time":11.03865722},
{"learn":[0.09195019912],"iteration":860,"passed_time":67.87334917,"remaining_time":10.9574861},
{"learn":[0.09193739214],"iteration":861,"passed_time":67.94064659,"remaining_time":10.87680885},
{"learn":[0.09191682037],"iteration":862,"passed_time":68.00769234,"remaining_time":10.79612265},
{"learn":[0.09190033315],"iteration":863,"passed_time":68.06797476,"remaining_time":10.71440343},
{"learn":[0.09184252303],"iteration":864,"passed_time":68.14170086,"remaining_time":10.63483193},
{"learn":[0.09182659065],"iteration":865,"passed_time":68.20453689,"remaining_time":10.55358885},
{"learn":[0.09181515673],"iteration":866,"passed_time":68.27218002,"remaining_time":10.47312565},
{"learn":[0.09179514112],"iteration":867,"passed_time":68.34335344,"remaining_time":10.39322886},
{"learn":[0.09177535183],"iteration":868,"passed_time":68.40893156,"remaining_time":10.31250867},
{"learn":[0.09174474082],"iteration":869,"passed_time":68.47588335,"remaining_time":10.23202855},
{"learn":[0.09172073684],"iteration":870,"passed_time":68.54631756,"remaining_time":10.15209525},
{"learn":[0.09170663728],"iteration":871,"passed_time":68.60744985,"remaining_time":10.07081833},
{"learn":[0.09169677394],"iteration":872,"passed_time":68.66685869,"remaining_time":9.989336832},
{"learn":[0.09167496137],"iteration":873,"passed_time":68.73363703,"remaining_time":9.908968267},
{"learn":[0.09162955787],"iteration":874,"passed_time":68.80259815,"remaining_time":9.828942592},
{"learn":[0.09160545932],"iteration":875,"passed_time":68.87385788,"remaining_time":9.749267554},
{"learn":[0.09158085909],"iteration":876,"passed_time":68.94311457,"remaining_time":9.669330778},
{"learn":[0.09154628581],"iteration":877,"passed_time":69.01197328,"remaining_time":9.58936303},
{"learn":[0.09152124522],"iteration":878,"passed_time":69.07761913,"remaining_time":9.508978288},
{"learn":[0.09148375023],"iteration":879,"passed_time":69.14763636,"remaining_time":9.42922314},
{"learn":[0.09146908695],"iteration":880,"passed_time":69.20854045,"remaining_time":9.348259153},
{"learn":[0.09144189889],"iteration":881,"passed_time":69.27796191,"remaining_time":9.268480165},
{"learn":[0.09141001097],"iteration":882,"passed_time":69.34809805,"remaining_time":9.188819334},
{"learn":[0.09140123214],"iteration":883,"passed_time":69.41049778,"remaining_time":9.108164867},
{"learn":[0.09137963581],"iteration":884,"passed_time":69.47853625,"remaining_time":9.028284371},
{"learn":[0.09135767261],"iteration":885,"passed_time":69.54410821,"remaining_time":8.948113245},
{"learn":[0.09132913057],"iteration":886,"passed_time":69.61553949,"remaining_time":8.86872149},
{"learn":[0.0913090477],"iteration":887,"passed_time":69.68087458,"remaining_time":8.788578776},
{"learn":[0.09128523241],"iteration":888,"passed_time":69.74713031,"remaining_time":8.708584324},
{"learn":[0.09125047185],"iteration":889,"passed_time":69.8163609,"remaining_time":8.628988426},
{"learn":[0.09122542495],"iteration":890,"passed_time":69.87991704,"remaining_time":8.548721613},
{"learn":[0.09120372615],"iteration":891,"passed_time":69.95056502,"remaining_time":8.469350922},
{"learn":[0.09119196894],"iteration":892,"passed_time":70.015209,"remaining_time":8.389280362},
{"learn":[0.09117954225],"iteration":893,"passed_time":70.07971859,"remaining_time":8.309228378},
{"learn":[0.09115562136],"iteration":894,"passed_time":70.14270531,"remaining_time":8.229032467},
{"learn":[0.09114098773],"iteration":895,"passed_time":70.2105979,"remaining_time":8.149444399},
{"learn":[0.09111998289],"iteration":896,"passed_time":70.27791385,"remaining_time":8.069816195},
{"learn":[0.09110757508],"iteration":897,"passed_time":70.3394108,"remaining_time":7.989554456},
{"learn":[0.09108412844],"iteration":898,"passed_time":70.40499603,"remaining_time":7.909793769},
{"learn":[0.0910634556],"iteration":899,"passed_time":70.46952117,"remaining_time":7.829946797},
{"learn":[0.09104687629],"iteration":900,"passed_time":70.52804242,"remaining_time":7.749474139},
{"learn":[0.09101372756],"iteration":901,"passed_time":70.59494963,"remaining_time":7.669961268},
{"learn":[0.09099278357],"iteration":902,"passed_time":70.66143211,"remaining_time":7.590430691},
{"learn":[0.09097637426],"iteration":903,"passed_time":70.72579124,"remaining_time":7.510703494},
{"learn":[0.09095698022],"iteration":904,"passed_time":70.78914353,"remaining_time":7.430904569},
{"learn":[0.09093892729],"iteration":905,"passed_time":70.85632861,"remaining_time":7.351539613},
{"learn":[0.0909265614],"iteration":906,"passed_time":70.92115555,"remaining_time":7.27195972},
{"learn":[0.09089202875],"iteration":907,"passed_time":70.99275698,"remaining_time":7.193098725},
{"learn":[0.09085854774],"iteration":908,"passed_time":71.06363329,"remaining_time":7.11418111},
{"learn":[0.09082768599],"iteration":909,"passed_time":71.12901655,"remaining_time":7.034737901},
{"learn":[0.09080622879],"iteration":910,"passed_time":71.19119477,"remaining_time":6.955012441},
{"learn":[0.09079100254],"iteration":911,"passed_time":71.25467045,"remaining_time":6.875450657},
{"learn":[0.09077296027],"iteration":912,"passed_time":71.31994701,"remaining_time":6.796095717},
{"learn":[0.09076307761],"iteration":913,"passed_time":71.38324213,"remaining_time":6.716585146},
{"learn":[0.09074718055],"iteration":914,"passed_time":71.45698065,"remaining_time":6.63808017},
{"learn":[0.09072429725],"iteration":915,"passed_time":71.52341191,"remaining_time":6.558915503},
{"learn":[0.09070750579],"iteration":916,"passed_time":71.58423325,"remaining_time":6.47927084},
{"learn":[0.09069141288],"iteration":917,"passed_time":71.64687493,"remaining_time":6.399829786},
{"learn":[0.09067379145],"iteration":918,"passed_time":71.70977382,"remaining_time":6.320447964},
{"learn":[0.09064874965],"iteration":919,"passed_time":71.77117089,"remaining_time":6.240971382},
{"learn":[0.0906308347],"iteration":920,"passed_time":71.85049324,"remaining_time":6.163071624},
{"learn":[0.09061411717],"iteration":921,"passed_time":71.9180115,"remaining_time":6.08417017},
{"learn":[0.09059746293],"iteration":922,"passed_time":71.98066023,"remaining_time":6.004887148},
{"learn":[0.09058264866],"iteration":923,"passed_time":72.05492538,"remaining_time":5.926595594},
{"learn":[0.09056253424],"iteration":924,"passed_time":72.11741633,"remaining_time":5.847358081},
{"learn":[0.09054776784],"iteration":925,"passed_time":72.17918468,"remaining_time":5.768098992},
{"learn":[0.09053276247],"iteration":926,"passed_time":72.24475359,"remaining_time":5.689176928},
{"learn":[0.09051669455],"iteration":927,"passed_time":72.31498413,"remaining_time":5.610645321},
{"learn":[0.09050343009],"iteration":928,"passed_time":72.37860022,"remaining_time":5.531626066},
{"learn":[0.09048278852],"iteration":929,"passed_time":72.44519214,"remaining_time":5.452863925},
{"learn":[0.09040192821],"iteration":930,"passed_time":72.51784372,"remaining_time":5.374577032},
{"learn":[0.09037934917],"iteration":931,"passed_time":72.60871803,"remaining_time":5.297631788},
{"learn":[0.09035962304],"iteration":932,"passed_time":72.68571197,"remaining_time":5.219659916},
{"learn":[0.09033967033],"iteration":933,"passed_time":72.75498692,"remaining_time":5.141144686},
{"learn":[0.09031872397],"iteration":934,"passed_time":72.81756717,"remaining_time":5.062183814},
{"learn":[0.09029439678],"iteration":935,"passed_time":72.88671316,"remaining_time":4.983706883},
{"learn":[0.0902791369],"iteration":936,"passed_time":72.95236721,"remaining_time":4.905015084},
{"learn":[0.09026430855],"iteration":937,"passed_time":73.01494643,"remaining_time":4.826147845},
{"learn":[0.09025308507],"iteration":938,"passed_time":73.08010733,"remaining_time":4.747483011},
{"learn":[0.09023366915],"iteration":939,"passed_time":73.1526814,"remaining_time":4.66932009},
{"learn":[0.09021065184],"iteration":940,"passed_time":73.21529215,"remaining_time":4.590544354},
{"learn":[0.09018197053],"iteration":941,"passed_time":73.28371345,"remaining_time":4.512160701},
{"learn":[0.09015985232],"iteration":942,"passed_time":73.35109999,"remaining_time":4.43373563},
{"learn":[0.09013875168],"iteration":943,"passed_time":73.41444075,"remaining_time":4.355093943},
{"learn":[0.09011579295],"iteration":944,"passed_time":73.47971408,"remaining_time":4.276597116},
{"learn":[0.09008865939],"iteration":945,"passed_time":73.55238017,"remaining_time":4.198550242},
{"learn":[0.09005941403],"iteration":946,"passed_time":73.62062315,"remaining_time":4.120267188},
{"learn":[0.09004181537],"iteration":947,"passed_time":73.68562302,"remaining_time":4.041827423},
{"learn":[0.09002066385],"iteration":948,"passed_time":73.74872043,"remaining_time":3.963313743},
{"learn":[0.09000630059],"iteration":949,"passed_time":73.82359105,"remaining_time":3.88545216},
{"learn":[0.08999171009],"iteration":950,"passed_time":73.90564901,"remaining_time":3.807967194},
{"learn":[0.08997647433],"iteration":951,"passed_time":73.98824074,"remaining_time":3.730499533},
{"learn":[0.08996013857],"iteration":952,"passed_time":74.0608701,"remaining_time":3.652529795},
{"learn":[0.08995239645],"iteration":953,"passed_time":74.1336076,"remaining_time":3.574576467},
{"learn":[0.08992446286],"iteration":954,"passed_time":74.21584124,"remaining_time":3.497081524},
{"learn":[0.08990260866],"iteration":955,"passed_time":74.28657447,"remaining_time":3.41904736},
{"learn":[0.0898806844],"iteration":956,"passed_time":74.36975285,"remaining_time":3.341587641},
{"learn":[0.08986082173],"iteration":957,"passed_time":74.44677961,"remaining_time":3.263846288},
{"learn":[0.08984415957],"iteration":958,"passed_time":74.53147923,"remaining_time":3.186434462},
{"learn":[0.08982433311],"iteration":959,"passed_time":74.61270472,"remaining_time":3.108862697},
{"learn":[0.08979301739],"iteration":960,"passed_time":74.69128974,"remaining_time":3.03117617},
{"learn":[0.08976563062],"iteration":961,"passed_time":74.76762486,"remaining_time":2.953398903},
{"learn":[0.08975190037],"iteration":962,"passed_time":74.84752959,"remaining_time":2.875761781},
{"learn":[0.08972288968],"iteration":963,"passed_time":74.92200373,"remaining_time":2.797917152},
{"learn":[0.08969789205],"iteration":964,"passed_time":74.99745678,"remaining_time":2.720115013},
{"learn":[0.08968768111],"iteration":965,"passed_time":75.07351302,"remaining_time":2.642338968},
{"learn":[0.08966698625],"iteration":966,"passed_time":75.13980075,"remaining_time":2.564233118},
{"learn":[0.08964905886],"iteration":967,"passed_time":75.21687641,"remaining_time":2.486508311},
{"learn":[0.0896250345],"iteration":968,"passed_time":75.28936257,"remaining_time":2.408638018},
{"learn":[0.08959374165],"iteration":969,"passed_time":75.36160618,"remaining_time":2.330771325},
{"learn":[0.08956757157],"iteration":970,"passed_time":75.43307076,"remaining_time":2.252892947},
{"learn":[0.08955372294],"iteration":971,"passed_time":75.50491941,"remaining_time":2.175038831},
{"learn":[0.08953457952],"iteration":972,"passed_time":75.58320599,"remaining_time":2.097375706},
{"learn":[0.08952299647],"iteration":973,"passed_time":75.66014546,"remaining_time":2.019675341},
{"learn":[0.08950695726],"iteration":974,"passed_time":75.73338279,"remaining_time":1.94188161},
{"learn":[0.08949548023],"iteration":975,"passed_time":75.80575028,"remaining_time":1.864075826},
{"learn":[0.08946972043],"iteration":976,"passed_time":75.88059319,"remaining_time":1.786339451},
{"learn":[0.08944816684],"iteration":977,"passed_time":75.95418381,"remaining_time":1.708580822},
{"learn":[0.08942520986],"iteration":978,"passed_time":76.03258224,"remaining_time":1.630933838},
{"learn":[0.08940237102],"iteration":979,"passed_time":76.09309273,"remaining_time":1.55292026},
{"learn":[0.08938400994],"iteration":980,"passed_time":76.16252586,"remaining_time":1.47511518},
{"learn":[0.08936041417],"iteration":981,"passed_time":76.22955051,"remaining_time":1.397283003},
{"learn":[0.08934610841],"iteration":982,"passed_time":76.30345445,"remaining_time":1.319591786},
{"learn":[0.08931572947],"iteration":983,"passed_time":76.37762963,"remaining_time":1.241912677},
{"learn":[0.08929226786],"iteration":984,"passed_time":76.44998525,"remaining_time":1.164212973},
{"learn":[0.08927499757],"iteration":985,"passed_time":76.5266849,"remaining_time":1.08658579},
{"learn":[0.08924568947],"iteration":986,"passed_time":76.60717787,"remaining_time":1.009010448},
{"learn":[0.08923564238],"iteration":987,"passed_time":76.676158,"remaining_time":0.9312893684},
{"learn":[0.08922149854],"iteration":988,"passed_time":76.74696957,"remaining_time":0.853606335},
{"learn":[0.08920578619],"iteration":989,"passed_time":76.82745789,"remaining_time":0.7760349282},
{"learn":[0.08918841766],"iteration":990,"passed_time":76.89923045,"remaining_time":0.6983784803},
{"learn":[0.08917132641],"iteration":991,"passed_time":76.96602894,"remaining_time":0.6206937818},
{"learn":[0.08915560609],"iteration":992,"passed_time":77.04417393,"remaining_time":0.5431109945},
{"learn":[0.08913513679],"iteration":993,"passed_time":77.12460225,"remaining_time":0.4655408587},
{"learn":[0.08911450918],"iteration":994,"passed_time":77.20023608,"remaining_time":0.3879408848},
{"learn":[0.08908544583],"iteration":995,"passed_time":77.28825604,"remaining_time":0.3103946026},
{"learn":[0.08906040947],"iteration":996,"passed_time":77.36719439,"remaining_time":0.2327999831},
{"learn":[0.08903771892],"iteration":997,"passed_time":77.44560739,"remaining_time":0.155201618},
{"learn":[0.08902959344],"iteration":998,"passed_time":77.5073354,"remaining_time":0.07758492032},
{"learn":[0.08901343216],"iteration":999,"passed_time":77.5820859,"remaining_time":0}
]}